{"lastUsed":1694531471598,"path":"D:\/java_Vtalent\/spring","projectCount":17,"recentFiles":[{"path":"\/collections\/src\/com\/collectionInterface","parentWorkspace":"D:\/java_Vtalent\/spring","name":"MyThread.java","lastModified":1692212143132,"locationURI":"file:\/D:\/java_Vtalent\/spring\/collections\/src\/com\/collectionInterface\/MyThread.java"},{"path":"\/com.classAssignments\/src\/com\/multiThreadImplemetnsRunnable","parentWorkspace":"D:\/java_Vtalent\/spring","name":"Customer2.java","lastModified":1689687010635,"locationURI":"file:\/D:\/java_Vtalent\/spring\/com.classAssignments\/src\/com\/multiThreadImplemetnsRunnable\/Customer2.java"},{"path":"\/trai1\/src\/com\/func","parentWorkspace":"D:\/java_Vtalent\/spring","name":"Test.java","lastModified":1691291362555,"locationURI":"file:\/D:\/java_Vtalent\/spring\/trai1\/src\/com\/func\/Test.java"},{"path":"\/com.classAssignments\/src\/com\/accessModifiers","parentWorkspace":"D:\/java_Vtalent\/spring","name":"CalculateAreaOfCircle.java","lastModified":1688125398549,"locationURI":"file:\/D:\/java_Vtalent\/spring\/com.classAssignments\/src\/com\/accessModifiers\/CalculateAreaOfCircle.java"},{"path":"\/Java8PPT\/src\/com\/functionalinterface","parentWorkspace":"D:\/java_Vtalent\/spring","name":"Demo.java","lastModified":1694278126015,"locationURI":"file:\/D:\/java_Vtalent\/spring\/Java8PPT\/src\/com\/functionalinterface\/Demo.java"},{"path":"\/com.classAssignments\/src\/com\/accessModifiers","parentWorkspace":"D:\/java_Vtalent\/spring","name":"PersonAddress.java","lastModified":1688185661868,"locationURI":"file:\/D:\/java_Vtalent\/spring\/com.classAssignments\/src\/com\/accessModifiers\/PersonAddress.java"},{"path":"\/com.classAssignments\/src\/com\/constructors","parentWorkspace":"D:\/java_Vtalent\/spring","name":"Example2.java","lastModified":1687402292945,"locationURI":"file:\/D:\/java_Vtalent\/spring\/com.classAssignments\/src\/com\/constructors\/Example2.java"},{"path":"\/java8\/src\/com\/streams","parentWorkspace":"D:\/java_Vtalent\/spring","name":"FindDuplictesInString.java","lastModified":1692583896861,"locationURI":"file:\/D:\/java_Vtalent\/spring\/java8\/src\/com\/streams\/FindDuplictesInString.java"},{"path":"\/com.classAssignments\/src\/com\/serialization","parentWorkspace":"D:\/java_Vtalent\/spring","name":"Transient.java","lastModified":1690385875955,"locationURI":"file:\/D:\/java_Vtalent\/spring\/com.classAssignments\/src\/com\/serialization\/Transient.java"},{"path":"\/secondSpring\/src\/main\/java\/com\/mavenexample\/secondSpring","parentWorkspace":"D:\/java_Vtalent\/spring","name":"Spring3.xml","lastModified":1693295282929,"locationURI":"file:\/D:\/java_Vtalent\/spring\/secondSpring\/src\/main\/java\/com\/mavenexample\/secondSpring\/Spring3.xml"},{"path":"\/com.classAssignments\/src\/com\/singletonDesignPattren","parentWorkspace":"D:\/java_Vtalent\/spring","name":"SingletonExp3.java","lastModified":1691638140736,"locationURI":"file:\/D:\/java_Vtalent\/spring\/com.classAssignments\/src\/com\/singletonDesignPattren\/SingletonExp3.java"},{"path":"\/FileHandling\/src\/com\/filehandling","parentWorkspace":"D:\/java_Vtalent\/spring","name":"Car.java","lastModified":1690383297030,"locationURI":"file:\/D:\/java_Vtalent\/spring\/FileHandling\/src\/com\/filehandling\/Car.java"},{"path":"\/com.classAssignments\/src\/com\/methodsOnStrings","parentWorkspace":"D:\/java_Vtalent\/spring","name":"permutationsRecursion.java","lastModified":1687229248914,"locationURI":"file:\/D:\/java_Vtalent\/spring\/com.classAssignments\/src\/com\/methodsOnStrings\/permutationsRecursion.java"},{"path":"\/com.classAssignments\/src\/com\/reviseStrings","parentWorkspace":"D:\/java_Vtalent\/spring","name":"TrimMethodInstrings.java","lastModified":1686637777943},{"path":"\/Java8PPT\/src\/com\/functionalinterface","parentWorkspace":"D:\/java_Vtalent\/spring","name":"FunctionExp1.java","lastModified":1694341452920,"locationURI":"file:\/D:\/java_Vtalent\/spring\/Java8PPT\/src\/com\/functionalinterface\/FunctionExp1.java"},{"path":"\/trai1\/src\/general_practice","parentWorkspace":"D:\/java_Vtalent\/spring","name":"normalPractice.java","lastModified":1684859967863},{"path":"\/com.classAssignments\/src\/com\/methodsOnStrings","parentWorkspace":"D:\/java_Vtalent\/spring","name":"StringConsistsOfSpecialCharacters.java","lastModified":1687137374904,"locationURI":"file:\/D:\/java_Vtalent\/spring\/com.classAssignments\/src\/com\/methodsOnStrings\/StringConsistsOfSpecialCharacters.java"},{"path":"\/trai1\/src\/com\/mahindra","parentWorkspace":"D:\/java_Vtalent\/spring","name":"Engine.java","lastModified":1688540431928,"locationURI":"file:\/D:\/java_Vtalent\/spring\/trai1\/src\/com\/mahindra\/Engine.java"},{"path":"\/java8\/src\/com\/functionalinterface","parentWorkspace":"D:\/java_Vtalent\/spring","name":"Student.java","lastModified":1691939651607,"locationURI":"file:\/D:\/java_Vtalent\/spring\/java8\/src\/com\/functionalinterface\/Student.java"},{"path":"\/com.classAssignments\/src\/com\/stringsAssignments","parentWorkspace":"D:\/java_Vtalent\/spring","name":"ReplaceMultipleCharactersInString.java","lastModified":1686299285534},{"path":"\/com.classAssignments\/src\/com\/stringsAssignments","parentWorkspace":"D:\/java_Vtalent\/spring","name":"SwappingPairsOfCharactersInStringPage4_2.java","lastModified":1687138501737},{"path":"\/com.classAssignments\/src\/com\/methodsOnStrings","parentWorkspace":"D:\/java_Vtalent\/spring","name":"CheckIfStringConsistsOnlySpecialCharactersPage_3_15.java","lastModified":1686898959735,"locationURI":"file:\/D:\/java_Vtalent\/spring\/com.classAssignments\/src\/com\/methodsOnStrings\/CheckIfStringConsistsOnlySpecialCharactersPage_3_15.java"},{"path":"\/com.classAssignments\/src\/com\/multiThreadImplemetnsRunnable","parentWorkspace":"D:\/java_Vtalent\/spring","name":"Exp1.java","lastModified":1689084729307,"locationURI":"file:\/D:\/java_Vtalent\/spring\/com.classAssignments\/src\/com\/multiThreadImplemetnsRunnable\/Exp1.java"},{"path":"\/java8\/src\/com\/collectorsStream","parentWorkspace":"D:\/java_Vtalent\/spring","name":"FindingCommonElementsInTwoLists.java","lastModified":1692443792135,"locationURI":"file:\/D:\/java_Vtalent\/spring\/java8\/src\/com\/collectorsStream\/FindingCommonElementsInTwoLists.java"},{"path":"\/java8\/src\/com\/collectorsStream","parentWorkspace":"D:\/java_Vtalent\/spring","name":"FilteringandSortingBooks.java","lastModified":1692707479920,"locationURI":"file:\/D:\/java_Vtalent\/spring\/java8\/src\/com\/collectorsStream\/FilteringandSortingBooks.java"},{"path":"\/com.classAssignments\/src\/com\/stringsAssignments","parentWorkspace":"D:\/java_Vtalent\/spring","name":"StringConsistsOfSpecialCharacters.java","lastModified":1686305746595},{"path":"\/oopsPractice\/src\/com\/inheritance","parentWorkspace":"D:\/java_Vtalent\/spring","name":"Parent1.java","lastModified":1688202175225,"locationURI":"file:\/D:\/java_Vtalent\/spring\/oopsPractice\/src\/com\/inheritance\/Parent1.java"},{"path":"\/trai1\/src","parentWorkspace":"D:\/java_Vtalent\/spring","name":"Mycomparator5.java","lastModified":1691340372604,"locationURI":"file:\/D:\/java_Vtalent\/spring\/trai1\/src\/Mycomparator5.java"},{"path":"\/collections\/src\/com\/collectionInterface","parentWorkspace":"D:\/java_Vtalent\/spring","name":"FindMaxKeyEntryInMap.java","lastModified":1691569696960,"locationURI":"file:\/D:\/java_Vtalent\/spring\/collections\/src\/com\/collectionInterface\/FindMaxKeyEntryInMap.java"},{"path":"\/java8\/src\/com\/optionalclass","parentWorkspace":"D:\/java_Vtalent\/spring","name":"OptionalClassRealTimeExample.java","lastModified":1692064960827,"locationURI":"file:\/D:\/java_Vtalent\/spring\/java8\/src\/com\/optionalclass\/OptionalClassRealTimeExample.java"},{"path":"\/com.classAssignments\/src\/com\/callableInterface","parentWorkspace":"D:\/java_Vtalent\/spring","name":"ThreadCallable.java","lastModified":1689736244489,"locationURI":"file:\/D:\/java_Vtalent\/spring\/com.classAssignments\/src\/com\/callableInterface\/ThreadCallable.java"},{"path":"\/collections","parentWorkspace":"D:\/java_Vtalent\/spring","name":"db1.properties","lastModified":1692184275757,"locationURI":"file:\/D:\/java_Vtalent\/spring\/collections\/db1.properties"},{"path":"\/java8\/src\/com\/streams","parentWorkspace":"D:\/java_Vtalent\/spring","name":"HowToFindDuplicateMaxValueMinValueElementsInList.java","lastModified":1692278503461,"locationURI":"file:\/D:\/java_Vtalent\/spring\/java8\/src\/com\/streams\/HowToFindDuplicateMaxValueMinValueElementsInList.java"},{"path":"\/com.classAssignments\/src\/com\/stringsPractice","parentWorkspace":"D:\/java_Vtalent\/spring","name":"HowToCompareStringsInJavaProblem12.java","lastModified":1686134164976},{"path":"\/com.classAssignments\/src\/com\/stringsAssignments","parentWorkspace":"D:\/java_Vtalent\/spring","name":"CheckIfStringConsistsOnlySpecialCharactersPage_3_15.java","lastModified":1686899325324},{"path":"\/com.classAssignments\/src\/com\/classAssignments8And9And10","parentWorkspace":"D:\/java_Vtalent\/spring","name":"FindAlllPalindromicSubStringsOfGivenString.java","lastModified":1686489261609},{"path":"\/com.classAssignments\/src\/com\/methodsOnStrings","parentWorkspace":"D:\/java_Vtalent\/spring","name":"SwappingPairsOfCharactersInStringPage4_2.java","lastModified":1687138445477,"locationURI":"file:\/D:\/java_Vtalent\/spring\/com.classAssignments\/src\/com\/methodsOnStrings\/SwappingPairsOfCharactersInStringPage4_2.java"},{"path":"\/com.classAssignments\/src\/com\/arrraysPractice","parentWorkspace":"D:\/java_Vtalent\/spring","name":"LargestNumberSmallestNumberProblem12And13.java","lastModified":1690473986614,"locationURI":"file:\/D:\/java_Vtalent\/spring\/com.classAssignments\/src\/com\/arrraysPractice\/LargestNumberSmallestNumberProblem12And13.java"},{"path":"\/com.classAssignments\/src\/com\/methodsOnStrings","parentWorkspace":"D:\/java_Vtalent\/spring","name":"IfStringContainsOnlyDigitsPage4_15.java","lastModified":1687135000053,"locationURI":"file:\/D:\/java_Vtalent\/spring\/com.classAssignments\/src\/com\/methodsOnStrings\/IfStringContainsOnlyDigitsPage4_15.java"},{"path":"\/com.classAssignments\/src\/com\/methodsOnStrings","parentWorkspace":"D:\/java_Vtalent\/spring","name":"SwapTwoStringsWithoutUsingAnyThirdVariable.java","lastModified":1687143039374,"locationURI":"file:\/D:\/java_Vtalent\/spring\/com.classAssignments\/src\/com\/methodsOnStrings\/SwapTwoStringsWithoutUsingAnyThirdVariable.java"},{"path":"\/com.classAssignments\/src\/com\/methodsOnStrings","parentWorkspace":"D:\/java_Vtalent\/spring","name":"PangramInJavaPage4_5.java","lastModified":1687136229874,"locationURI":"file:\/D:\/java_Vtalent\/spring\/com.classAssignments\/src\/com\/methodsOnStrings\/PangramInJavaPage4_5.java"},{"path":"\/com.classAssignments\/src\/com\/classAssignments8And9And10","parentWorkspace":"D:\/java_Vtalent\/spring","name":"RemoveLeadingZerosFromString9_2.java","lastModified":1686910335935},{"path":"\/com.classAssignments\/src\/com\/multiThreadImplemetnsRunnable","parentWorkspace":"D:\/java_Vtalent\/spring","name":"JoinMethodDemo.java","lastModified":1689163584465,"locationURI":"file:\/D:\/java_Vtalent\/spring\/com.classAssignments\/src\/com\/multiThreadImplemetnsRunnable\/JoinMethodDemo.java"},{"path":"\/collections\/src","parentWorkspace":"D:\/java_Vtalent\/spring","name":"RemoveDuplicates.java","lastModified":1691899212122,"locationURI":"file:\/D:\/java_Vtalent\/spring\/collections\/src\/RemoveDuplicates.java"},{"path":"\/java8\/src\/com\/streams","parentWorkspace":"D:\/java_Vtalent\/spring","name":"Employees.java","lastModified":1692627294196,"locationURI":"file:\/D:\/java_Vtalent\/spring\/java8\/src\/com\/streams\/Employees.java"},{"path":"\/com.classAssignments\/src\/com\/arrraysPractice","parentWorkspace":"D:\/java_Vtalent\/spring","name":"MultiDimentional3DArrayProblem2.java","lastModified":1690483201268,"locationURI":"file:\/D:\/java_Vtalent\/spring\/com.classAssignments\/src\/com\/arrraysPractice\/MultiDimentional3DArrayProblem2.java"},{"path":"\/java8\/src\/com\/streams","parentWorkspace":"D:\/java_Vtalent\/spring","name":"SecondMaxAndSecondMin.java","lastModified":1693020479823,"locationURI":"file:\/D:\/java_Vtalent\/spring\/java8\/src\/com\/streams\/SecondMaxAndSecondMin.java"},{"path":"\/com.classAssignments\/src\/com\/stringsAssignments","parentWorkspace":"D:\/java_Vtalent\/spring","name":"IfStringContainsOnlyDigitsPage4_15.java","lastModified":1687134869144},{"path":"\/com.classAssignments\/src\/com\/arrraysPractice","parentWorkspace":"D:\/java_Vtalent\/spring","name":"HowToSortArrayProblem15.java","lastModified":1690476813915,"locationURI":"file:\/D:\/java_Vtalent\/spring\/com.classAssignments\/src\/com\/arrraysPractice\/HowToSortArrayProblem15.java"},{"path":"\/com.classAssignments\/src\/com\/stringsAssignments","parentWorkspace":"D:\/java_Vtalent\/spring","name":"PangramInJavaPage4_5.java","lastModified":1687136344916},{"path":"\/com.classAssignments\/src\/com\/methodsOnStrings","parentWorkspace":"D:\/java_Vtalent\/spring","name":"RemoveDuplicatesFromString.java","lastModified":1687139060494,"locationURI":"file:\/D:\/java_Vtalent\/spring\/com.classAssignments\/src\/com\/methodsOnStrings\/RemoveDuplicatesFromString.java"},{"path":"\/com.classAssignments\/src\/com\/methodsOnStrings","parentWorkspace":"D:\/java_Vtalent\/spring","name":"RemoveAllNonAlphanumericCharactersFromStringPage4_12.java","lastModified":1687136954290,"locationURI":"file:\/D:\/java_Vtalent\/spring\/com.classAssignments\/src\/com\/methodsOnStrings\/RemoveAllNonAlphanumericCharactersFromStringPage4_12.java"},{"path":"\/Java8PPT\/src\/com\/functionalinterface","parentWorkspace":"D:\/java_Vtalent\/spring","name":"SupplierExp1.java","lastModified":1694341315290,"locationURI":"file:\/D:\/java_Vtalent\/spring\/Java8PPT\/src\/com\/functionalinterface\/SupplierExp1.java"},{"path":"\/java8\/src\/com\/streams","parentWorkspace":"D:\/java_Vtalent\/spring","name":"MapExp2AverageSalary.java","lastModified":1692331394973,"locationURI":"file:\/D:\/java_Vtalent\/spring\/java8\/src\/com\/streams\/MapExp2AverageSalary.java"},{"path":"\/com.classAssignments\/src\/com\/stringsAssignments","parentWorkspace":"D:\/java_Vtalent\/spring","name":"ExtractSingleQuoteEnclosedStringPahe2_9.java","lastModified":1686318946334},{"path":"\/com.classAssignments\/src\/com\/stringsAssignments","parentWorkspace":"D:\/java_Vtalent\/spring","name":"ConvertStringToFloatValue.java","lastModified":1686296887434},{"path":"\/com.classAssignments\/src\/com\/arrraysPractice","parentWorkspace":"D:\/java_Vtalent\/spring","name":"Exp1.java","lastModified":1690471974069,"locationURI":"file:\/D:\/java_Vtalent\/spring\/com.classAssignments\/src\/com\/arrraysPractice\/Exp1.java"},{"path":"\/collections\/src\/com\/collectionInterface","parentWorkspace":"D:\/java_Vtalent\/spring","name":"CompareToExample.java","lastModified":1692203603738,"locationURI":"file:\/D:\/java_Vtalent\/spring\/collections\/src\/com\/collectionInterface\/CompareToExample.java"},{"path":"\/com.classAssignments\/src\/com\/reviseStrings","parentWorkspace":"D:\/java_Vtalent\/spring","name":"Harsh.java","lastModified":1686753970753,"locationURI":"file:\/D:\/java_Vtalent\/spring\/com.classAssignments\/src\/com\/reviseStrings\/Harsh.java"},{"path":"\/com.classAssignments\/src\/com\/methodsOnStrings","parentWorkspace":"D:\/java_Vtalent\/spring","name":"CheckIfStringContainsOnlyAlphabetsPage4_11.java","lastModified":1686982587358,"locationURI":"file:\/D:\/java_Vtalent\/spring\/com.classAssignments\/src\/com\/methodsOnStrings\/CheckIfStringContainsOnlyAlphabetsPage4_11.java"},{"path":"\/collections\/src\/com\/collectionInterface","parentWorkspace":"D:\/java_Vtalent\/spring","name":"ArrayListCapacity.java","lastModified":1692195737027,"locationURI":"file:\/D:\/java_Vtalent\/spring\/collections\/src\/com\/collectionInterface\/ArrayListCapacity.java"},{"path":"\/com.classAssignments\/src\/com\/multiThreadingExtendningThreadClass","parentWorkspace":"D:\/java_Vtalent\/spring","name":"Demo1.java","lastModified":1688989791289,"locationURI":"file:\/D:\/java_Vtalent\/spring\/com.classAssignments\/src\/com\/multiThreadingExtendningThreadClass\/Demo1.java"},{"path":"\/FirstSpring\/src\/main\/java\/com\/mavenexample\/FirstSpring","parentWorkspace":"D:\/java_Vtalent\/spring","name":"BillCollector.java","lastModified":1692978008810,"locationURI":"file:\/D:\/java_Vtalent\/spring\/FirstSpring\/src\/main\/java\/com\/mavenexample\/FirstSpring\/BillCollector.java"},{"path":"\/trai1\/src\/general_practice","parentWorkspace":"D:\/java_Vtalent\/spring","name":"demo.java","lastModified":1684576494766},{"path":"\/com.classAssignments\/src\/com\/stringsAssignments","parentWorkspace":"D:\/java_Vtalent\/spring","name":"RemoveAllNonAlphanumericCharactersFromStringPage4_12.java","lastModified":1686477586319},{"path":"\/com.classAssignments\/src\/com\/accessModifiers","parentWorkspace":"D:\/java_Vtalent\/spring","name":"Access1.java","lastModified":1687399574816,"locationURI":"file:\/D:\/java_Vtalent\/spring\/com.classAssignments\/src\/com\/accessModifiers\/Access1.java"},{"path":"\/java8\/src\/com\/streams","parentWorkspace":"D:\/java_Vtalent\/spring","name":"SortDesecndingOrderbasedOnEmployeeSalary.java","lastModified":1692416329785,"locationURI":"file:\/D:\/java_Vtalent\/spring\/java8\/src\/com\/streams\/SortDesecndingOrderbasedOnEmployeeSalary.java"},{"path":"\/com.classAssignments\/src\/com\/classAssignments8And9And10","parentWorkspace":"D:\/java_Vtalent\/spring","name":"RemovingWhiteSpacesUsingRegexInJava8_4.java","lastModified":1686489510836},{"path":"\/com.classAssignments\/src\/com\/stringsAssignments","parentWorkspace":"D:\/java_Vtalent\/spring","name":"PrintMiddleCharacterOfStringPage4_4.java","lastModified":1687136492844,"locationURI":"file:\/D:\/java_Vtalent\/spring\/com.classAssignments\/src\/com\/stringsAssignments\/PrintMiddleCharacterOfStringPage4_4.java"},{"path":"\/com.classAssignments\/src\/com\/stringsAssignments","parentWorkspace":"D:\/java_Vtalent\/spring","name":"JavaProgramToPrintNewLineInString.java","lastModified":1686297684055},{"path":"\/com.classAssignments\/src\/com\/accessModifiers","parentWorkspace":"D:\/java_Vtalent\/spring","name":"HasARelation.java","lastModified":1688125398549,"locationURI":"file:\/D:\/java_Vtalent\/spring\/com.classAssignments\/src\/com\/accessModifiers\/HasARelation.java"},{"path":"\/SpringbootFirst\/src\/main\/java\/com\/examplespringboot","parentWorkspace":"D:\/java_Vtalent\/spring","name":"SpringbootFirstApplication.java","lastModified":1694484549757,"locationURI":"file:\/D:\/java_Vtalent\/spring\/SpringbootFirst\/src\/main\/java\/com\/examplespringboot\/SpringbootFirstApplication.java"},{"path":"\/trai1\/src","parentWorkspace":"D:\/java_Vtalent\/spring","name":"Demo.java","lastModified":1687321779001,"locationURI":"file:\/D:\/java_Vtalent\/spring\/trai1\/src\/Demo.java"},{"path":"\/springFramework\/src\/com\/strategyDesignPattren","parentWorkspace":"D:\/java_Vtalent\/spring","name":"DeditCard.java","lastModified":1692689801278,"locationURI":"file:\/D:\/java_Vtalent\/spring\/springFramework\/src\/com\/strategyDesignPattren\/DeditCard.java"},{"path":"\/com.classAssignments\/src\/com\/exceptionsHandling","parentWorkspace":"D:\/java_Vtalent\/spring","name":"ArthamaticExeption5_1.java","lastModified":1688745801186,"locationURI":"file:\/D:\/java_Vtalent\/spring\/com.classAssignments\/src\/com\/exceptionsHandling\/ArthamaticExeption5_1.java"},{"path":"\/com.classAssignments\/src\/com\/stringsAssignments","parentWorkspace":"D:\/java_Vtalent\/spring","name":"CheckIfStringContainsOnlyAlphabetsPage4_11.java","lastModified":1686899848057},{"path":"\/FirstSpring\/src\/main\/java\/com\/mavenexample\/FirstSpring","parentWorkspace":"D:\/java_Vtalent\/spring","name":"UPI.java","lastModified":1692978008910,"locationURI":"file:\/D:\/java_Vtalent\/spring\/FirstSpring\/src\/main\/java\/com\/mavenexample\/FirstSpring\/UPI.java"},{"path":"\/com.classAssignments\/src\/com\/methodsOnStrings","parentWorkspace":"D:\/java_Vtalent\/spring","name":"JavaProgramFindTheLostNumberPage2_11.java","lastModified":1687135184434,"locationURI":"file:\/D:\/java_Vtalent\/spring\/com.classAssignments\/src\/com\/methodsOnStrings\/JavaProgramFindTheLostNumberPage2_11.java"},{"path":"\/com.classAssignments\/src\/com\/inheritance","parentWorkspace":"D:\/java_Vtalent\/spring","name":"Test1.java","lastModified":1687748087198,"locationURI":"file:\/D:\/java_Vtalent\/spring\/com.classAssignments\/src\/com\/inheritance\/Test1.java"},{"path":"\/DateAndTime\/src\/com\/datedemo","parentWorkspace":"D:\/java_Vtalent\/spring","name":"DurationDemo.java","lastModified":1693019716887,"locationURI":"file:\/D:\/java_Vtalent\/spring\/DateAndTime\/src\/com\/datedemo\/DurationDemo.java"},{"path":"\/trai1\/src\/com\/func","parentWorkspace":"D:\/java_Vtalent\/spring","name":"Myinterface.java","lastModified":1691242004488,"locationURI":"file:\/D:\/java_Vtalent\/spring\/trai1\/src\/com\/func\/Myinterface.java"},{"path":"\/com.classAssignments\/src\/com\/methodsOnStrings","parentWorkspace":"D:\/java_Vtalent\/spring","name":"PrintMiddleCharacterOfStringPage4_4.java","lastModified":1687136492855,"locationURI":"file:\/D:\/java_Vtalent\/spring\/com.classAssignments\/src\/com\/methodsOnStrings\/PrintMiddleCharacterOfStringPage4_4.java"},{"path":"\/com.classAssignments\/src\/com\/classAssignments8And9And10","parentWorkspace":"D:\/java_Vtalent\/spring","name":"AnagramStrings.java","lastModified":1686728429146},{"path":"\/com.classAssignments\/src\/com\/classAssignments8And9And10","parentWorkspace":"D:\/java_Vtalent\/spring","name":"SortString2DifferentWays.java","lastModified":1686910335935},{"path":"\/com.classAssignments\/src\/com\/methodsOnStrings","parentWorkspace":"D:\/java_Vtalent\/spring","name":"permutationsIteration.java","lastModified":1687156302636,"locationURI":"file:\/D:\/java_Vtalent\/spring\/com.classAssignments\/src\/com\/methodsOnStrings\/permutationsIteration.java"},{"path":"\/com.classAssignments\/src\/com\/reviseStrings","parentWorkspace":"D:\/java_Vtalent\/spring","name":"SearchingForCharactersAndSubstringInString.java","lastModified":1686728429147},{"path":"\/com.classAssignments\/src\/com\/strings\/assignments\/page5","parentWorkspace":"D:\/java_Vtalent\/spring","name":"ConvertStringValueToFloatValueProb5_7.java","lastModified":1686480564684},{"path":"\/com.classAssignments\/src\/com\/stringsAssignments","parentWorkspace":"D:\/java_Vtalent\/spring","name":"JavaProgramFindTheLostNumberPage2_11.java","lastModified":1687135184418},{"path":"\/com.classAssignments\/src\/com\/inheritance","parentWorkspace":"D:\/java_Vtalent\/spring","name":"Test.java","lastModified":1688125398549,"locationURI":"file:\/D:\/java_Vtalent\/spring\/com.classAssignments\/src\/com\/inheritance\/Test.java"},{"path":"\/java8\/src\/com\/streams","parentWorkspace":"D:\/java_Vtalent\/spring","name":"FileLinesAndFilesWrite.java","lastModified":1692689602222,"locationURI":"file:\/D:\/java_Vtalent\/spring\/java8\/src\/com\/streams\/FileLinesAndFilesWrite.java"},{"path":"\/com.classAssignments\/src\/com\/methodsOnStrings","parentWorkspace":"D:\/java_Vtalent\/spring","name":"Practice1.java","lastModified":1687262277370,"locationURI":"file:\/D:\/java_Vtalent\/spring\/com.classAssignments\/src\/com\/methodsOnStrings\/Practice1.java"},{"path":"\/com.classAssignments\/src\/com\/accessModifiers","parentWorkspace":"D:\/java_Vtalent\/spring","name":"test.java","lastModified":1687858100508,"locationURI":"file:\/D:\/java_Vtalent\/spring\/com.classAssignments\/src\/com\/accessModifiers\/test.java"},{"path":"\/com.classAssignments\/src\/com\/methodsOnStrings","parentWorkspace":"D:\/java_Vtalent\/spring","name":"JavaProgramMoveAllUppercaseCharactersToEndPage2_5.java","lastModified":1687135381463,"locationURI":"file:\/D:\/java_Vtalent\/spring\/com.classAssignments\/src\/com\/methodsOnStrings\/JavaProgramMoveAllUppercaseCharactersToEndPage2_5.java"},{"path":"\/trai1\/src\/trai1","parentWorkspace":"D:\/java_Vtalent\/spring","name":"A.java","lastModified":1690901733426,"locationURI":"file:\/D:\/java_Vtalent\/spring\/trai1\/src\/trai1\/A.java"},{"path":"\/FirstSpring\/src\/main\/java","parentWorkspace":"D:\/java_Vtalent\/spring","name":"spring2.xml","lastModified":1692985629143,"locationURI":"file:\/D:\/java_Vtalent\/spring\/FirstSpring\/src\/main\/java\/spring2.xml"},{"path":"\/com.classAssignments\/src\/com\/stringsAssignments","parentWorkspace":"D:\/java_Vtalent\/spring","name":"PrintSmallestAndBiggestPossiblePalindromeWordGivenStringPage3_2.java","lastModified":1687136636695},{"path":"\/com.classAssignments\/src\/com\/arrraysPractice","parentWorkspace":"D:\/java_Vtalent\/spring","name":"ObjectArray.java","lastModified":1691826934356,"locationURI":"file:\/D:\/java_Vtalent\/spring\/com.classAssignments\/src\/com\/arrraysPractice\/ObjectArray.java"},{"path":"\/java8\/src\/com\/streams","parentWorkspace":"D:\/java_Vtalent\/spring","name":"FlatMapExp.java","lastModified":1692322377875,"locationURI":"file:\/D:\/java_Vtalent\/spring\/java8\/src\/com\/streams\/FlatMapExp.java"},{"path":"\/Java8PPT\/src\/com\/streams","parentWorkspace":"D:\/java_Vtalent\/spring","name":"Employees.java","lastModified":1694057885874,"locationURI":"file:\/D:\/java_Vtalent\/spring\/Java8PPT\/src\/com\/streams\/Employees.java"},{"path":"\/java8\/src\/com\/streams","parentWorkspace":"D:\/java_Vtalent\/spring","name":"StreamDemo1.java","lastModified":1692069277730,"locationURI":"file:\/D:\/java_Vtalent\/spring\/java8\/src\/com\/streams\/StreamDemo1.java"},{"path":"\/com.classAssignments\/src\/com\/multiThreadImplemetnsRunnable","parentWorkspace":"D:\/java_Vtalent\/spring","name":"Banking.java","lastModified":1689736244399,"locationURI":"file:\/D:\/java_Vtalent\/spring\/com.classAssignments\/src\/com\/multiThreadImplemetnsRunnable\/Banking.java"},{"path":"\/com.classAssignments\/src\/com\/arrraysPractice","parentWorkspace":"D:\/java_Vtalent\/spring","name":"RemoveElementFromArrayProblem23.java","lastModified":1686555265233},{"path":"\/com.classAssignments\/src\/com\/stringsPractice","parentWorkspace":"D:\/java_Vtalent\/spring","name":"StringPatternProgramsProblem8.java","lastModified":1686063219830},{"path":"\/com.classAssignments\/src\/com\/methodsOnStrings","parentWorkspace":"D:\/java_Vtalent\/spring","name":"ConvertSnakeCaseStringToCamelCasePage4_8.java","lastModified":1686935391883,"locationURI":"file:\/D:\/java_Vtalent\/spring\/com.classAssignments\/src\/com\/methodsOnStrings\/ConvertSnakeCaseStringToCamelCasePage4_8.java"},{"path":"\/com.classAssignments\/src\/com\/methodsOnStrings","parentWorkspace":"D:\/java_Vtalent\/spring","name":"PrintSmallestAndBiggestPossiblePalindromeWordGivenStringPage3_2.java","lastModified":1687136619104,"locationURI":"file:\/D:\/java_Vtalent\/spring\/com.classAssignments\/src\/com\/methodsOnStrings\/PrintSmallestAndBiggestPossiblePalindromeWordGivenStringPage3_2.java"},{"path":"\/com.classAssignments\/src\/com\/reviseStrings","parentWorkspace":"D:\/java_Vtalent\/spring","name":"RecursiveApproch.java","lastModified":1686748581169},{"path":"\/com.classAssignments\/src\/com\/stringsPractice","parentWorkspace":"D:\/java_Vtalent\/spring","name":"ConvertStringToFloatValue.java","lastModified":1686295687360},{"path":"\/oopsPractice\/src\/com\/encapsulation","parentWorkspace":"D:\/java_Vtalent\/spring","name":"Practice2.java","lastModified":1687421194334,"locationURI":"file:\/D:\/java_Vtalent\/spring\/oopsPractice\/src\/com\/encapsulation\/Practice2.java"},{"path":"\/oopsPractice\/src\/com\/encapsulation","parentWorkspace":"D:\/java_Vtalent\/spring","name":"BankAccount.java","lastModified":1687497126263,"locationURI":"file:\/D:\/java_Vtalent\/spring\/oopsPractice\/src\/com\/encapsulation\/BankAccount.java"},{"path":"\/com.classAssignments\/src\/com\/stringsAssignments","parentWorkspace":"D:\/java_Vtalent\/spring","name":"ConvertSnakeCaseStringToCamelCasePage4_8.java","lastModified":1686925838237},{"path":"\/com.classAssignments\/src\/com\/reviseStrings","parentWorkspace":"D:\/java_Vtalent\/spring","name":"RemoveDuplicatesFromString.java","lastModified":1686746574044,"locationURI":"file:\/D:\/java_Vtalent\/spring\/com.classAssignments\/src\/com\/reviseStrings\/RemoveDuplicatesFromString.java"},{"path":"\/com.classAssignments\/src\/com\/stringsAssignments","parentWorkspace":"D:\/java_Vtalent\/spring","name":"DifferentWaysToPrintFirstKCharactersInStringPage4_3.java","lastModified":1687134418721},{"path":"\/com.classAssignments\/src\/com\/multiThreadingExtendningThreadClass","parentWorkspace":"D:\/java_Vtalent\/spring","name":"ClassB.java","lastModified":1689523746025,"locationURI":"file:\/D:\/java_Vtalent\/spring\/com.classAssignments\/src\/com\/multiThreadingExtendningThreadClass\/ClassB.java"},{"path":"\/com.classAssignments\/src\/com\/classAssignments8And9And10","parentWorkspace":"D:\/java_Vtalent\/spring","name":"CheckStringContainsOnlyAlphabetsJava8_1.java","lastModified":1686486646156},{"path":"\/com.classAssignments\/src\/com\/stringsPractice","parentWorkspace":"D:\/java_Vtalent\/spring","name":"InputFromConsoleProblem1.java","lastModified":1686049325503},{"path":"\/com.classAssignments\/src\/com\/methodsOnStrings","parentWorkspace":"D:\/java_Vtalent\/spring","name":"Demo.java","lastModified":1687281320130,"locationURI":"file:\/D:\/java_Vtalent\/spring\/com.classAssignments\/src\/com\/methodsOnStrings\/Demo.java"},{"path":"\/oopsPractice\/src\/com\/inheritance","parentWorkspace":"D:\/java_Vtalent\/spring","name":"Test1.java","lastModified":1690598432364,"locationURI":"file:\/D:\/java_Vtalent\/spring\/oopsPractice\/src\/com\/inheritance\/Test1.java"},{"path":"\/Java8PPT\/src\/com\/defaultMethods","parentWorkspace":"D:\/java_Vtalent\/spring","name":"Jio.java","lastModified":1693237724465,"locationURI":"file:\/D:\/java_Vtalent\/spring\/Java8PPT\/src\/com\/defaultMethods\/Jio.java"},{"path":"\/com.classAssignments\/src\/com\/stringsAssignments","parentWorkspace":"D:\/java_Vtalent\/spring","name":"RemoveUppercaseLowercaseSpecialNumericNonNumericCharactersPage3_5.java","lastModified":1687137245069},{"path":"\/com.classAssignments\/src\/com\/classAssignments8And9And10","parentWorkspace":"D:\/java_Vtalent\/spring","name":"JavaprogramToExpandStringIfRangeIsGiven8_7.java","lastModified":1686500133544},{"path":"\/com.classAssignments\/src\/com\/collections","parentWorkspace":"D:\/java_Vtalent\/spring","name":"ValidateBracket.java","lastModified":1691342772789,"locationURI":"file:\/D:\/java_Vtalent\/spring\/com.classAssignments\/src\/com\/collections\/ValidateBracket.java"},{"path":"\/FirstSpring","parentWorkspace":"D:\/java_Vtalent\/spring","name":"pom.xml","lastModified":1692975548468,"locationURI":"file:\/D:\/java_Vtalent\/spring\/FirstSpring\/pom.xml"},{"path":"\/com.classAssignments\/src\/com\/exceptionsHandling","parentWorkspace":"D:\/java_Vtalent\/spring","name":"ExceptionExp2.java","lastModified":1688640425449,"locationURI":"file:\/D:\/java_Vtalent\/spring\/com.classAssignments\/src\/com\/exceptionsHandling\/ExceptionExp2.java"},{"path":"\/Java8PPT\/src\/com\/java8\/collectionsenhancements","parentWorkspace":"D:\/java_Vtalent\/spring","name":"Employee.java","lastModified":1693549156874,"locationURI":"file:\/D:\/java_Vtalent\/spring\/Java8PPT\/src\/com\/java8\/collectionsenhancements\/Employee.java"},{"path":"\/com.classAssignments\/src\/com\/stringsAssignments","parentWorkspace":"D:\/java_Vtalent\/spring","name":"OptimizeStringConcatenationInJavapage3_3.java","lastModified":1686389048232},{"path":"\/FirstSpring\/src\/main\/java\/com\/mavenexample\/FirstSpring","parentWorkspace":"D:\/java_Vtalent\/spring","name":"Test.java","lastModified":1693327002837,"locationURI":"file:\/D:\/java_Vtalent\/spring\/FirstSpring\/src\/main\/java\/com\/mavenexample\/FirstSpring\/Test.java"},{"path":"\/com.classAssignments\/src\/com\/reviseStrings","parentWorkspace":"D:\/java_Vtalent\/spring","name":"StringPermutations.java","lastModified":1687139148790,"locationURI":"file:\/D:\/java_Vtalent\/spring\/com.classAssignments\/src\/com\/reviseStrings\/StringPermutations.java"},{"path":"\/com.classAssignments\/src\/com\/reviseStrings","parentWorkspace":"D:\/java_Vtalent\/spring","name":"PrintAllUniqueWords.java","lastModified":1686910335935},{"path":"\/java8\/src\/com\/streams","parentWorkspace":"D:\/java_Vtalent\/spring","name":"InterviewTaksOnStreams.java","lastModified":1693273902555,"locationURI":"file:\/D:\/java_Vtalent\/spring\/java8\/src\/com\/streams\/InterviewTaksOnStreams.java"},{"path":"\/com.classAssignments\/src\/com\/multiThreadImplemetnsRunnable","parentWorkspace":"D:\/java_Vtalent\/spring","name":"JoinExp2.java","lastModified":1689560568192,"locationURI":"file:\/D:\/java_Vtalent\/spring\/com.classAssignments\/src\/com\/multiThreadImplemetnsRunnable\/JoinExp2.java"},{"path":"\/com.classAssignments\/src\/com\/stringsAssignments","parentWorkspace":"D:\/java_Vtalent\/spring","name":"CountNumberOfDigitsInStringPage3_1.java","lastModified":1686983035160},{"path":"\/collections\/src\/com\/collectionInterface","parentWorkspace":"D:\/java_Vtalent\/spring","name":"ComparableOnStrings.java","lastModified":1692211962183,"locationURI":"file:\/D:\/java_Vtalent\/spring\/collections\/src\/com\/collectionInterface\/ComparableOnStrings.java"},{"path":"\/com.classAssignments\/src\/com\/stringsPractice","parentWorkspace":"D:\/java_Vtalent\/spring","name":"CountNoOfVowelsStringProblem7.java","lastModified":1686317153785},{"path":"\/com.classAssignments\/src\/com\/exceptionsHandling","parentWorkspace":"D:\/java_Vtalent\/spring","name":"EligibleVote.java","lastModified":1688919743649,"locationURI":"file:\/D:\/java_Vtalent\/spring\/com.classAssignments\/src\/com\/exceptionsHandling\/EligibleVote.java"},{"path":"\/com.classAssignments\/src\/com\/methodsOnStrings","parentWorkspace":"D:\/java_Vtalent\/spring","name":"Driver.java","lastModified":1686986598101,"locationURI":"file:\/D:\/java_Vtalent\/spring\/com.classAssignments\/src\/com\/methodsOnStrings\/Driver.java"},{"path":"\/DateAndTime\/src\/com\/datedemo","parentWorkspace":"D:\/java_Vtalent\/spring","name":"LeapYearDemo.java","lastModified":1693019051343,"locationURI":"file:\/D:\/java_Vtalent\/spring\/DateAndTime\/src\/com\/datedemo\/LeapYearDemo.java"},{"path":"\/com.classAssignments\/src\/com\/classAssignments8And9And10","parentWorkspace":"D:\/java_Vtalent\/spring","name":"PrintNumberOfWordsVowelsAndFrequencyOfEachCharacter8_8.java","lastModified":1686502736234},{"path":"\/com.classAssignments\/src\/com\/arrraysPractice","parentWorkspace":"D:\/java_Vtalent\/spring","name":"PrintAlternativeEvenNumbersArraysproblem41.java","lastModified":1690478182914,"locationURI":"file:\/D:\/java_Vtalent\/spring\/com.classAssignments\/src\/com\/arrraysPractice\/PrintAlternativeEvenNumbersArraysproblem41.java"},{"path":"\/Java8PPT\/src\/com\/methodrefernace","parentWorkspace":"D:\/java_Vtalent\/spring","name":"MethodReferanceExample1.java","lastModified":1693937857485,"locationURI":"file:\/D:\/java_Vtalent\/spring\/Java8PPT\/src\/com\/methodrefernace\/MethodReferanceExample1.java"},{"path":"\/com.classAssignments\/src\/com\/methodsOnStrings","parentWorkspace":"D:\/java_Vtalent\/spring","name":"CountNumberOfDigitsInStringPage3_1.java","lastModified":1686984157968,"locationURI":"file:\/D:\/java_Vtalent\/spring\/com.classAssignments\/src\/com\/methodsOnStrings\/CountNumberOfDigitsInStringPage3_1.java"},{"path":"\/com.classAssignments\/src\/com\/methodsOnStrings","parentWorkspace":"D:\/java_Vtalent\/spring","name":"RemoveUppercaseLowercaseSpecialNumericNonNumericCharactersPage3_5.java","lastModified":1687137255401,"locationURI":"file:\/D:\/java_Vtalent\/spring\/com.classAssignments\/src\/com\/methodsOnStrings\/RemoveUppercaseLowercaseSpecialNumericNonNumericCharactersPage3_5.java"},{"path":"\/java8\/src\/com\/streams","parentWorkspace":"D:\/java_Vtalent\/spring","name":"GroupAndCountExample.java","lastModified":1692418568600,"locationURI":"file:\/D:\/java_Vtalent\/spring\/java8\/src\/com\/streams\/GroupAndCountExample.java"},{"path":"\/Java8PPT\/src\/com\/defaultMethods","parentWorkspace":"D:\/java_Vtalent\/spring","name":"MutlipleInheritanceMain.java","lastModified":1692669262031,"locationURI":"file:\/D:\/java_Vtalent\/spring\/Java8PPT\/src\/com\/defaultMethods\/MutlipleInheritanceMain.java"},{"path":"\/com.classAssignments\/src\/com\/stringsPractice","parentWorkspace":"D:\/java_Vtalent\/spring","name":"AddingCharacterAsThousandsSeparatorToGivenNumberPage3_5.java","lastModified":1686470766528},{"path":"\/FirstSpring\/src\/main\/java\/com\/mavenexample\/FirstSpring","parentWorkspace":"D:\/java_Vtalent\/spring","name":"DebitCard.java","lastModified":1692978009013,"locationURI":"file:\/D:\/java_Vtalent\/spring\/FirstSpring\/src\/main\/java\/com\/mavenexample\/FirstSpring\/DebitCard.java"},{"path":"\/com.classAssignments\/src\/com\/reviseStrings","parentWorkspace":"D:\/java_Vtalent\/spring","name":"CompareTwoStrings.java","lastModified":1686728429147},{"path":"\/FirstSpring\/src\/main\/java\/com\/mavenexample\/FirstSpring","parentWorkspace":"D:\/java_Vtalent\/spring","name":"Psw.java","lastModified":1694404265506,"locationURI":"file:\/D:\/java_Vtalent\/spring\/FirstSpring\/src\/main\/java\/com\/mavenexample\/FirstSpring\/Psw.java"},{"path":"\/java8\/src\/com\/streams","parentWorkspace":"D:\/java_Vtalent\/spring","name":"MapDemo.java","lastModified":1692349584098,"locationURI":"file:\/D:\/java_Vtalent\/spring\/java8\/src\/com\/streams\/MapDemo.java"},{"path":"\/DateAndTime\/src\/com\/datedemo","parentWorkspace":"D:\/java_Vtalent\/spring","name":"DateDemo.java","lastModified":1693634721655,"locationURI":"file:\/D:\/java_Vtalent\/spring\/DateAndTime\/src\/com\/datedemo\/DateDemo.java"},{"path":"\/com.classAssignments\/src\/com\/classAssignmentsPage6And7","parentWorkspace":"D:\/java_Vtalent\/spring","name":"ConvertStringToDate.java","lastModified":1686722819330},{"path":"\/java8\/src\/com\/functionalinterface","parentWorkspace":"D:\/java_Vtalent\/spring","name":"AnonymousAndLambda.java","lastModified":1693327094429,"locationURI":"file:\/D:\/java_Vtalent\/spring\/java8\/src\/com\/functionalinterface\/AnonymousAndLambda.java"},{"path":"\/collections\/src\/com\/collectionInterface","parentWorkspace":"D:\/java_Vtalent\/spring","name":"Vector1.java","lastModified":1691858589301,"locationURI":"file:\/D:\/java_Vtalent\/spring\/collections\/src\/com\/collectionInterface\/Vector1.java"},{"path":"\/com.classAssignments\/src\/com\/arrraysPractice","parentWorkspace":"D:\/java_Vtalent\/spring","name":"Exp3.java","lastModified":1690598524517,"locationURI":"file:\/D:\/java_Vtalent\/spring\/com.classAssignments\/src\/com\/arrraysPractice\/Exp3.java"},{"path":"\/com.classAssignments\/src\/com\/collections","parentWorkspace":"D:\/java_Vtalent\/spring","name":"A.java","lastModified":1691422098167,"locationURI":"file:\/D:\/java_Vtalent\/spring\/com.classAssignments\/src\/com\/collections\/A.java"},{"path":"\/com.classAssignments\/src\/com\/strings\/assignments\/page5","parentWorkspace":"D:\/java_Vtalent\/spring","name":"CheckIfStringIsNullProb5_11.java","lastModified":1686480862724},{"path":"\/com.classAssignments\/src\/com\/multiThreadImplemetnsRunnable","parentWorkspace":"D:\/java_Vtalent\/spring","name":"Test.java","lastModified":1689161357497,"locationURI":"file:\/D:\/java_Vtalent\/spring\/com.classAssignments\/src\/com\/multiThreadImplemetnsRunnable\/Test.java"},{"path":"\/trai1\/src","parentWorkspace":"D:\/java_Vtalent\/spring","name":"ComparableComparator.java","lastModified":1691340372430,"locationURI":"file:\/D:\/java_Vtalent\/spring\/trai1\/src\/ComparableComparator.java"},{"path":"\/FirstSpring\/src\/main\/java\/com\/mavenexample\/FirstSpring","parentWorkspace":"D:\/java_Vtalent\/spring","name":"Payment.java","lastModified":1692978008934,"locationURI":"file:\/D:\/java_Vtalent\/spring\/FirstSpring\/src\/main\/java\/com\/mavenexample\/FirstSpring\/Payment.java"},{"path":"\/com.classAssignments\/src\/com\/singletonDesignPattren","parentWorkspace":"D:\/java_Vtalent\/spring","name":"singletonExp1.java","lastModified":1689746267404,"locationURI":"file:\/D:\/java_Vtalent\/spring\/com.classAssignments\/src\/com\/singletonDesignPattren\/singletonExp1.java"},{"path":"\/com.classAssignments\/src\/com\/arrraysPractice","parentWorkspace":"D:\/java_Vtalent\/spring","name":"GetArrayInputProblem2.java","lastModified":1690473305008,"locationURI":"file:\/D:\/java_Vtalent\/spring\/com.classAssignments\/src\/com\/arrraysPractice\/GetArrayInputProblem2.java"},{"path":"\/Java8PPT\/src\/com\/stringjoiner","parentWorkspace":"D:\/java_Vtalent\/spring","name":"StringJoinerExp1.java","lastModified":1694345661229,"locationURI":"file:\/D:\/java_Vtalent\/spring\/Java8PPT\/src\/com\/stringjoiner\/StringJoinerExp1.java"},{"path":"\/FirstSpring\/src\/main\/java\/com\/mavenexample\/FirstSpring","parentWorkspace":"D:\/java_Vtalent\/spring","name":"CreditCard.java","lastModified":1692978009261,"locationURI":"file:\/D:\/java_Vtalent\/spring\/FirstSpring\/src\/main\/java\/com\/mavenexample\/FirstSpring\/CreditCard.java"},{"path":"\/com.classAssignments\/src\/com\/multiThreadImplemetnsRunnable","parentWorkspace":"D:\/java_Vtalent\/spring","name":"MyThread.java","lastModified":1690598366365,"locationURI":"file:\/D:\/java_Vtalent\/spring\/com.classAssignments\/src\/com\/multiThreadImplemetnsRunnable\/MyThread.java"},{"path":"\/trai1\/src\/trai1","parentWorkspace":"D:\/java_Vtalent\/spring","name":"ArrayListExp.java","lastModified":1692607624172,"locationURI":"file:\/D:\/java_Vtalent\/spring\/trai1\/src\/trai1\/ArrayListExp.java"},{"path":"\/Java8PPT\/src\/com\/defaultMethods","parentWorkspace":"D:\/java_Vtalent\/spring","name":"Airtel.java","lastModified":1693187636432,"locationURI":"file:\/D:\/java_Vtalent\/spring\/Java8PPT\/src\/com\/defaultMethods\/Airtel.java"},{"path":"\/springFramework\/src\/com\/strategyDesignPattren","parentWorkspace":"D:\/java_Vtalent\/spring","name":"Upi.java","lastModified":1692974899589,"locationURI":"file:\/D:\/java_Vtalent\/spring\/springFramework\/src\/com\/strategyDesignPattren\/Upi.java"},{"path":"\/com.classAssignments\/src\/com\/strings\/assignments\/page5","parentWorkspace":"D:\/java_Vtalent\/spring","name":"HowToConvertArrayToStringProb13.java","lastModified":1686482274825},{"path":"\/com.classAssignments\/src\/com\/multiThreadImplemetnsRunnable","parentWorkspace":"D:\/java_Vtalent\/spring","name":"Customer1.java","lastModified":1689687288235,"locationURI":"file:\/D:\/java_Vtalent\/spring\/com.classAssignments\/src\/com\/multiThreadImplemetnsRunnable\/Customer1.java"},{"path":"\/com.classAssignments\/src\/com\/stringsAssignments","parentWorkspace":"D:\/java_Vtalent\/spring","name":"ConvertCamelCaseStringToSnakeCasePage4_10.java","lastModified":1686902635110,"locationURI":"file:\/D:\/java_Vtalent\/spring\/com.classAssignments\/src\/com\/stringsAssignments\/ConvertCamelCaseStringToSnakeCasePage4_10.java"},{"path":"\/collections\/src\/com\/maps","parentWorkspace":"D:\/java_Vtalent\/spring","name":"PropertiesExp.java","lastModified":1692195160146,"locationURI":"file:\/D:\/java_Vtalent\/spring\/collections\/src\/com\/maps\/PropertiesExp.java"},{"path":"\/com.classAssignments\/src\/com\/exceptionsHandling","parentWorkspace":"D:\/java_Vtalent\/spring","name":"ExceptionExp3.java","lastModified":1688735593104,"locationURI":"file:\/D:\/java_Vtalent\/spring\/com.classAssignments\/src\/com\/exceptionsHandling\/ExceptionExp3.java"},{"path":"\/FileHandling\/src\/com\/filehandling","parentWorkspace":"D:\/java_Vtalent\/spring","name":"fileHandle.java","lastModified":1690383882106,"locationURI":"file:\/D:\/java_Vtalent\/spring\/FileHandling\/src\/com\/filehandling\/fileHandle.java"},{"path":"\/collections\/src\/com\/collectionInterface","parentWorkspace":"D:\/java_Vtalent\/spring","name":"ArrayList1.java","lastModified":1691827647244,"locationURI":"file:\/D:\/java_Vtalent\/spring\/collections\/src\/com\/collectionInterface\/ArrayList1.java"},{"path":"\/oopsPractice\/src\/com\/encapsulation","parentWorkspace":"D:\/java_Vtalent\/spring","name":"Practice1.java","lastModified":1687409738129,"locationURI":"file:\/D:\/java_Vtalent\/spring\/oopsPractice\/src\/com\/encapsulation\/Practice1.java"},{"path":"\/com.classAssignments\/src\/com\/reviseStrings","parentWorkspace":"D:\/java_Vtalent\/spring","name":"ReverseAString.java","lastModified":1686728429147},{"path":"\/com.classAssignments\/src\/com\/methodsOnStrings","parentWorkspace":"D:\/java_Vtalent\/spring","name":"ConvertCamelCaseStringToSnakeCasePage4_10.java","lastModified":1686902578191,"locationURI":"file:\/D:\/java_Vtalent\/spring\/com.classAssignments\/src\/com\/methodsOnStrings\/ConvertCamelCaseStringToSnakeCasePage4_10.java"},{"path":"\/com.classAssignments\/src\/com\/arrraysPractice","parentWorkspace":"D:\/java_Vtalent\/spring","name":"secondLargestWithRepated.java","lastModified":1690480550089,"locationURI":"file:\/D:\/java_Vtalent\/spring\/com.classAssignments\/src\/com\/arrraysPractice\/secondLargestWithRepated.java"},{"path":"\/com.classAssignments\/src\/com\/classAssignments8And9And10","parentWorkspace":"D:\/java_Vtalent\/spring","name":"ProgramCheckValidMobileNumber8_9.java","lastModified":1686503605015},{"path":"\/com.classAssignments\/src\/com\/classAssignmentsPage6And7","parentWorkspace":"D:\/java_Vtalent\/spring","name":"ConvertListOfStringToCommaSeparatedString5.java","lastModified":1686484887169},{"path":"\/com.classAssignments\/src\/com\/multiThreadingExtendningThreadClass","parentWorkspace":"D:\/java_Vtalent\/spring","name":"MultiThreadSleepMethod.java","lastModified":1689161347972,"locationURI":"file:\/D:\/java_Vtalent\/spring\/com.classAssignments\/src\/com\/multiThreadingExtendningThreadClass\/MultiThreadSleepMethod.java"},{"path":"\/com.classAssignments\/src\/com\/stringsPractice","parentWorkspace":"D:\/java_Vtalent\/spring","name":"IteratethroughStringJavaProblem4.java","lastModified":1686050314026},{"path":"\/com.classAssignments\/src\/com\/stringsAssignments","parentWorkspace":"D:\/java_Vtalent\/spring","name":"ConvertingStringToIntergerArray.java","lastModified":1687107422567},{"path":"\/com.classAssignments\/src\/com\/singletonDesignPattren","parentWorkspace":"D:\/java_Vtalent\/spring","name":"SingletonExp4.java","lastModified":1691638140736,"locationURI":"file:\/D:\/java_Vtalent\/spring\/com.classAssignments\/src\/com\/singletonDesignPattren\/SingletonExp4.java"},{"path":"\/oopsPractice\/src\/com\/inheritance","parentWorkspace":"D:\/java_Vtalent\/spring","name":"Child1.java","lastModified":1688216844842,"locationURI":"file:\/D:\/java_Vtalent\/spring\/oopsPractice\/src\/com\/inheritance\/Child1.java"},{"path":"\/com.classAssignments\/src\/com\/arrraysPractice","parentWorkspace":"D:\/java_Vtalent\/spring","name":"RemoveDuplicatesFromArrayProblem20.java","lastModified":1690482135704},{"path":"\/com.classAssignments\/src\/com\/arrraysPractice","parentWorkspace":"D:\/java_Vtalent\/spring","name":"Reversearr.java","lastModified":1691763292137,"locationURI":"file:\/D:\/java_Vtalent\/spring\/com.classAssignments\/src\/com\/arrraysPractice\/Reversearr.java"},{"path":"\/com.classAssignments\/src\/com\/classAssignmentsPage6And7","parentWorkspace":"D:\/java_Vtalent\/spring","name":"CheckStringStartsWithAnyGivenPrefixes7_1.java","lastModified":1686486380532},{"path":"\/Java8PPT\/src\/com\/streams","parentWorkspace":"D:\/java_Vtalent\/spring","name":"FilterExpample1.java","lastModified":1694340125056,"locationURI":"file:\/D:\/java_Vtalent\/spring\/Java8PPT\/src\/com\/streams\/FilterExpample1.java"},{"path":"\/com.classAssignments\/src\/com\/methodsOnStrings","parentWorkspace":"D:\/java_Vtalent\/spring","name":"ConvertingStringToIntergerArray.java","lastModified":1686903160105,"locationURI":"file:\/D:\/java_Vtalent\/spring\/com.classAssignments\/src\/com\/methodsOnStrings\/ConvertingStringToIntergerArray.java"},{"path":"\/trai1\/src","parentWorkspace":"D:\/java_Vtalent\/spring","name":"Lamda1.java","lastModified":1691242004825,"locationURI":"file:\/D:\/java_Vtalent\/spring\/trai1\/src\/Lamda1.java"},{"path":"\/Java8PPT\/src\/com\/streams","parentWorkspace":"D:\/java_Vtalent\/spring","name":"Demo1.java","lastModified":1694362247207,"locationURI":"file:\/D:\/java_Vtalent\/spring\/Java8PPT\/src\/com\/streams\/Demo1.java"},{"path":"\/ntpersonalPractice\/src\/com\/innerClasses","parentWorkspace":"D:\/java_Vtalent\/spring","name":"MemberClass.java","lastModified":1687497122535,"locationURI":"file:\/D:\/java_Vtalent\/spring\/ntpersonalPractice\/src\/com\/innerClasses\/MemberClass.java"},{"path":"\/com.classAssignments\/src\/com\/strings\/assignments\/page5","parentWorkspace":"D:\/java_Vtalent\/spring","name":"HowToPadStringProb1.java","lastModified":1686479826781},{"path":"\/com.classAssignments\/src\/com\/exceptionsHandling","parentWorkspace":"D:\/java_Vtalent\/spring","name":"ExceptionHandlingExp4.java","lastModified":1688744297803,"locationURI":"file:\/D:\/java_Vtalent\/spring\/com.classAssignments\/src\/com\/exceptionsHandling\/ExceptionHandlingExp4.java"},{"path":"\/com.classAssignments\/src\/com\/generics","parentWorkspace":"D:\/java_Vtalent\/spring","name":"Emp.java","lastModified":1691081022672,"locationURI":"file:\/D:\/java_Vtalent\/spring\/com.classAssignments\/src\/com\/generics\/Emp.java"},{"path":"\/collections\/src\/com\/collectionInterface","parentWorkspace":"D:\/java_Vtalent\/spring","name":"ArrayList2.java","lastModified":1691827714436,"locationURI":"file:\/D:\/java_Vtalent\/spring\/collections\/src\/com\/collectionInterface\/ArrayList2.java"},{"path":"\/java8\/src\/com\/optionalclass","parentWorkspace":"D:\/java_Vtalent\/spring","name":"Demo.java","lastModified":1692287682587,"locationURI":"file:\/D:\/java_Vtalent\/spring\/java8\/src\/com\/optionalclass\/Demo.java"},{"path":"\/com.classAssignments\/src\/com\/exceptionsHandling","parentWorkspace":"D:\/java_Vtalent\/spring","name":"UserDfndExc.java","lastModified":1689051403045,"locationURI":"file:\/D:\/java_Vtalent\/spring\/com.classAssignments\/src\/com\/exceptionsHandling\/UserDfndExc.java"},{"path":"\/Java8PPT\/src\/com\/defaultMethods","parentWorkspace":"D:\/java_Vtalent\/spring","name":"User.java","lastModified":1693204554709,"locationURI":"file:\/D:\/java_Vtalent\/spring\/Java8PPT\/src\/com\/defaultMethods\/User.java"},{"path":"\/com.classAssignments\/src\/com\/arrraysPractice","parentWorkspace":"D:\/java_Vtalent\/spring","name":"PalindromArray.java","lastModified":1690482421494},{"path":"\/java8\/src\/com\/functionalinterface","parentWorkspace":"D:\/java_Vtalent\/spring","name":"ConstructorReferenceExample.java","lastModified":1692280499103,"locationURI":"file:\/D:\/java_Vtalent\/spring\/java8\/src\/com\/functionalinterface\/ConstructorReferenceExample.java"},{"path":"\/Java8PPT\/src\/com\/streams","parentWorkspace":"D:\/java_Vtalent\/spring","name":"EmployeeDatabase.java","lastModified":1694069598502,"locationURI":"file:\/D:\/java_Vtalent\/spring\/Java8PPT\/src\/com\/streams\/EmployeeDatabase.java"},{"path":"\/com.classAssignments\/src\/com\/multiThreadImplemetnsRunnable","parentWorkspace":"D:\/java_Vtalent\/spring","name":"Demo1.java","lastModified":1689643232130,"locationURI":"file:\/D:\/java_Vtalent\/spring\/com.classAssignments\/src\/com\/multiThreadImplemetnsRunnable\/Demo1.java"},{"path":"\/java8\/src\/com\/streams","parentWorkspace":"D:\/java_Vtalent\/spring","name":"Students.java","lastModified":1692327551719,"locationURI":"file:\/D:\/java_Vtalent\/spring\/java8\/src\/com\/streams\/Students.java"},{"path":"\/secondSpring\/src\/main\/java\/com\/mavenexample\/secondSpring","parentWorkspace":"D:\/java_Vtalent\/spring","name":"DieselEngine.java","lastModified":1693275842663,"locationURI":"file:\/D:\/java_Vtalent\/spring\/secondSpring\/src\/main\/java\/com\/mavenexample\/secondSpring\/DieselEngine.java"},{"path":"\/com.classAssignments\/src\/com\/reviseStrings","parentWorkspace":"D:\/java_Vtalent\/spring","name":"SwapTwoStringsWithoutUsingAnyThirdVariable.java","lastModified":1686636344047},{"path":"\/com.classAssignments\/src\/com\/stringsAssignments","parentWorkspace":"D:\/java_Vtalent\/spring","name":"ConvertStringToStringArrayUsingRegularExpressionPage2_8.java","lastModified":1686316844246},{"path":"\/com.classAssignments\/src\/com\/methodsOnStrings","parentWorkspace":"D:\/java_Vtalent\/spring","name":"FindAllPalindromicSubStringsOfStringPage2_2.java","lastModified":1687134484657,"locationURI":"file:\/D:\/java_Vtalent\/spring\/com.classAssignments\/src\/com\/methodsOnStrings\/FindAllPalindromicSubStringsOfStringPage2_2.java"},{"path":"\/com.classAssignments\/src\/com\/exceptionsHandling","parentWorkspace":"D:\/java_Vtalent\/spring","name":"AgeLimit.java","lastModified":1688920039354,"locationURI":"file:\/D:\/java_Vtalent\/spring\/com.classAssignments\/src\/com\/exceptionsHandling\/AgeLimit.java"},{"path":"\/Java8PPT\/src\/com\/streams","parentWorkspace":"D:\/java_Vtalent\/spring","name":"DistintMethodExample.java","lastModified":1693625658262,"locationURI":"file:\/D:\/java_Vtalent\/spring\/Java8PPT\/src\/com\/streams\/DistintMethodExample.java"},{"path":"\/com.classAssignments\/src\/com\/stringsPractice","parentWorkspace":"D:\/java_Vtalent\/spring","name":"Addition.java","lastModified":1686907789554,"locationURI":"file:\/D:\/java_Vtalent\/spring\/com.classAssignments\/src\/com\/stringsPractice\/Addition.java"},{"path":"\/java8\/src\/com\/optionalclass","parentWorkspace":"D:\/java_Vtalent\/spring","name":"Customer.java","lastModified":1691980957897,"locationURI":"file:\/D:\/java_Vtalent\/spring\/java8\/src\/com\/optionalclass\/Customer.java"},{"path":"\/java8\/src\/com\/streams","parentWorkspace":"D:\/java_Vtalent\/spring","name":"Employee.java","lastModified":1692349584098,"locationURI":"file:\/D:\/java_Vtalent\/spring\/java8\/src\/com\/streams\/Employee.java"},{"path":"\/java8\/src\/com\/streams","parentWorkspace":"D:\/java_Vtalent\/spring","name":"CollectorsExp1.java","lastModified":1694404265310,"locationURI":"file:\/D:\/java_Vtalent\/spring\/java8\/src\/com\/streams\/CollectorsExp1.java"},{"path":"\/com.classAssignments\/src\/com\/constructors","parentWorkspace":"D:\/java_Vtalent\/spring","name":"example1.java","lastModified":1687319360022,"locationURI":"file:\/D:\/java_Vtalent\/spring\/com.classAssignments\/src\/com\/constructors\/example1.java"},{"path":"\/java8\/src\/com\/streams","parentWorkspace":"D:\/java_Vtalent\/spring","name":"User.java","lastModified":1692069277738,"locationURI":"file:\/D:\/java_Vtalent\/spring\/java8\/src\/com\/streams\/User.java"},{"path":"\/Java8PPT\/src\/com\/streams","parentWorkspace":"D:\/java_Vtalent\/spring","name":"StreamvsPrarallelSteam.java","lastModified":1694146729084,"locationURI":"file:\/D:\/java_Vtalent\/spring\/Java8PPT\/src\/com\/streams\/StreamvsPrarallelSteam.java"},{"path":"\/oopsPractice\/src\/com\/encapsulation","parentWorkspace":"D:\/java_Vtalent\/spring","name":"BankApplication.java","lastModified":1688202241284,"locationURI":"file:\/D:\/java_Vtalent\/spring\/oopsPractice\/src\/com\/encapsulation\/BankApplication.java"},{"path":"\/com.classAssignments\/src\/com\/stringsAssignments","parentWorkspace":"D:\/java_Vtalent\/spring","name":"FindAllPalindromicSubStringsOfStringPage2_2.java","lastModified":1687134589955},{"path":"\/com.classAssignments\/src\/com\/methodsOnStrings","parentWorkspace":"D:\/java_Vtalent\/spring","name":"Aa.java","lastModified":1687281320110,"locationURI":"file:\/D:\/java_Vtalent\/spring\/com.classAssignments\/src\/com\/methodsOnStrings\/Aa.java"},{"path":"\/com.classAssignments\/src\/com\/singletonDesignPattren","parentWorkspace":"D:\/java_Vtalent\/spring","name":"SingletonExp2.java","lastModified":1691638140736,"locationURI":"file:\/D:\/java_Vtalent\/spring\/com.classAssignments\/src\/com\/singletonDesignPattren\/SingletonExp2.java"},{"path":"\/DateAndTime\/src\/com\/datedemo","parentWorkspace":"D:\/java_Vtalent\/spring","name":"PeriodDemo.java","lastModified":1693018839957,"locationURI":"file:\/D:\/java_Vtalent\/spring\/DateAndTime\/src\/com\/datedemo\/PeriodDemo.java"},{"path":"\/com.classAssignments\/src\/com\/classAssignments8And9And10","parentWorkspace":"D:\/java_Vtalent\/spring","name":"StringContainsOnlyAlphabetsInJavaUsingAsciiValues8_2.java","lastModified":1686488002674},{"path":"\/collections\/src\/com\/maps","parentWorkspace":"D:\/java_Vtalent\/spring","name":"Exp1.java","lastModified":1691758872312,"locationURI":"file:\/D:\/java_Vtalent\/spring\/collections\/src\/com\/maps\/Exp1.java"},{"path":"\/com.classAssignments\/src\/com\/methodsOnStrings","parentWorkspace":"D:\/java_Vtalent\/spring","name":"SwappingCharactersOfStringInJava.java","lastModified":1687139205960,"locationURI":"file:\/D:\/java_Vtalent\/spring\/com.classAssignments\/src\/com\/methodsOnStrings\/SwappingCharactersOfStringInJava.java"},{"path":"\/com.classAssignments\/src\/com\/generics","parentWorkspace":"D:\/java_Vtalent\/spring","name":"Exp2.java","lastModified":1691081022672,"locationURI":"file:\/D:\/java_Vtalent\/spring\/com.classAssignments\/src\/com\/generics\/Exp2.java"},{"path":"\/com.classAssignments\/src\/com\/classAssignmentsPage6And7","parentWorkspace":"D:\/java_Vtalent\/spring","name":"ReplaceCharacterAtSpecificIndexInString6.java","lastModified":1686485243055},{"path":"\/com.classAssignments\/src\/com\/exceptionsHandling","parentWorkspace":"D:\/java_Vtalent\/spring","name":"ExceptionExp1.java","lastModified":1688640150602,"locationURI":"file:\/D:\/java_Vtalent\/spring\/com.classAssignments\/src\/com\/exceptionsHandling\/ExceptionExp1.java"},{"path":"\/Java8PPT\/src\/com\/localtimeanddate","parentWorkspace":"D:\/java_Vtalent\/spring","name":"ClassA.java","lastModified":1693625658226,"locationURI":"file:\/D:\/java_Vtalent\/spring\/Java8PPT\/src\/com\/localtimeanddate\/ClassA.java"},{"path":"\/java8\/src\/com\/streams","parentWorkspace":"D:\/java_Vtalent\/spring","name":"Matching.java","lastModified":1692272205403,"locationURI":"file:\/D:\/java_Vtalent\/spring\/java8\/src\/com\/streams\/Matching.java"},{"path":"\/Java8PPT\/src\/com\/functionalinterface","parentWorkspace":"D:\/java_Vtalent\/spring","name":"PredicateExp1.java","lastModified":1694340485320,"locationURI":"file:\/D:\/java_Vtalent\/spring\/Java8PPT\/src\/com\/functionalinterface\/PredicateExp1.java"},{"path":"\/com.classAssignments\/src\/com\/arrraysPractice","parentWorkspace":"D:\/java_Vtalent\/spring","name":"ReverseArrayProblem16.java","lastModified":1690479950163,"locationURI":"file:\/D:\/java_Vtalent\/spring\/com.classAssignments\/src\/com\/arrraysPractice\/ReverseArrayProblem16.java"},{"path":"\/com.classAssignments\/src\/com\/methodsOnStrings","parentWorkspace":"D:\/java_Vtalent\/spring","name":"demo1.java","lastModified":1687283012760,"locationURI":"file:\/D:\/java_Vtalent\/spring\/com.classAssignments\/src\/com\/methodsOnStrings\/demo1.java"},{"path":"\/FileHandling\/src\/com\/filehandling","parentWorkspace":"D:\/java_Vtalent\/spring","name":"Exp1.java","lastModified":1690279695564,"locationURI":"file:\/D:\/java_Vtalent\/spring\/FileHandling\/src\/com\/filehandling\/Exp1.java"},{"path":"\/com.classAssignments\/src\/com\/stringsPractice","parentWorkspace":"D:\/java_Vtalent\/spring","name":"SortStringInJavaProblem11.java","lastModified":1686132986441},{"path":"\/com.classAssignments\/src\/com\/classAssignments8And9And10","parentWorkspace":"D:\/java_Vtalent\/spring","name":"JavaprogramToExpandStringIfRangeIsGiven8_6.java","lastModified":1686499985817},{"path":"\/com.classAssignments\/src\/com\/inheritance","parentWorkspace":"D:\/java_Vtalent\/spring","name":"Student.java","lastModified":1688125398549,"locationURI":"file:\/D:\/java_Vtalent\/spring\/com.classAssignments\/src\/com\/inheritance\/Student.java"},{"path":"\/com.classAssignments\/src\/com\/stringsPractice","parentWorkspace":"D:\/java_Vtalent\/spring","name":"StringContainsUppercaseOrLowercaseProblem15.java","lastModified":1686139314381},{"path":"\/com.classAssignments\/src\/com\/multiThreadingExtendningThreadClass","parentWorkspace":"D:\/java_Vtalent\/spring","name":"Test.java","lastModified":1689523746812,"locationURI":"file:\/D:\/java_Vtalent\/spring\/com.classAssignments\/src\/com\/multiThreadingExtendningThreadClass\/Test.java"},{"path":"\/java8\/src\/com\/functionalinterface","parentWorkspace":"D:\/java_Vtalent\/spring","name":"ComparatorLambdaExample.java","lastModified":1691980467983,"locationURI":"file:\/D:\/java_Vtalent\/spring\/java8\/src\/com\/functionalinterface\/ComparatorLambdaExample.java"},{"path":"\/com.classAssignments\/src\/com\/multiThreadImplemetnsRunnable","parentWorkspace":"D:\/java_Vtalent\/spring","name":"Demo3.java","lastModified":1689643232130,"locationURI":"file:\/D:\/java_Vtalent\/spring\/com.classAssignments\/src\/com\/multiThreadImplemetnsRunnable\/Demo3.java"},{"path":"\/com.classAssignments\/src\/com\/multiThreadingExtendningThreadClass","parentWorkspace":"D:\/java_Vtalent\/spring","name":"ClassA.java","lastModified":1689523746006,"locationURI":"file:\/D:\/java_Vtalent\/spring\/com.classAssignments\/src\/com\/multiThreadingExtendningThreadClass\/ClassA.java"},{"path":"\/Java8PPT\/src\/com\/defaultMethods","parentWorkspace":"D:\/java_Vtalent\/spring","name":"Test.java","lastModified":1693204554702,"locationURI":"file:\/D:\/java_Vtalent\/spring\/Java8PPT\/src\/com\/defaultMethods\/Test.java"},{"path":"\/com.classAssignments\/src\/com\/multiThreadingExtendningThreadClass","parentWorkspace":"D:\/java_Vtalent\/spring","name":"Multithread.java","lastModified":1688961736481,"locationURI":"file:\/D:\/java_Vtalent\/spring\/com.classAssignments\/src\/com\/multiThreadingExtendningThreadClass\/Multithread.java"},{"path":"\/java8\/src\/com\/collectorsStream","parentWorkspace":"D:\/java_Vtalent\/spring","name":"CollectorsRealWorldExamples.java","lastModified":1692432232422,"locationURI":"file:\/D:\/java_Vtalent\/spring\/java8\/src\/com\/collectorsStream\/CollectorsRealWorldExamples.java"},{"path":"\/com.classAssignments\/src\/com\/stringsAssignments","parentWorkspace":"D:\/java_Vtalent\/spring","name":"DetermineUnicodeCodePointAtGivenIndexInStringPage3_4.java","lastModified":1687134345551},{"path":"\/java8\/src\/com\/streams","parentWorkspace":"D:\/java_Vtalent\/spring","name":"MaoExp4AllMatch.java","lastModified":1692326941048,"locationURI":"file:\/D:\/java_Vtalent\/spring\/java8\/src\/com\/streams\/MaoExp4AllMatch.java"},{"path":"\/DateAndTime\/src\/com\/datedemo","parentWorkspace":"D:\/java_Vtalent\/spring","name":"LocatTimeInJava8.java","lastModified":1693017587302,"locationURI":"file:\/D:\/java_Vtalent\/spring\/DateAndTime\/src\/com\/datedemo\/LocatTimeInJava8.java"},{"path":"\/com.classAssignments\/src\/com\/generics","parentWorkspace":"D:\/java_Vtalent\/spring","name":"HighestKeyValue.java","lastModified":1691690621384,"locationURI":"file:\/D:\/java_Vtalent\/spring\/com.classAssignments\/src\/com\/generics\/HighestKeyValue.java"},{"path":"\/com.classAssignments\/src\/com\/reviseStrings","parentWorkspace":"D:\/java_Vtalent\/spring","name":"SwappingCharactersOfStringInJava.java","lastModified":1686649923612},{"path":"\/collections\/src\/com\/collectionInterface","parentWorkspace":"D:\/java_Vtalent\/spring","name":"HashSetMethods.java","lastModified":1692172148520,"locationURI":"file:\/D:\/java_Vtalent\/spring\/collections\/src\/com\/collectionInterface\/HashSetMethods.java"},{"path":"\/com.classAssignments\/src\/com\/strings\/assignments\/page5","parentWorkspace":"D:\/java_Vtalent\/spring","name":"ConvertFloatValueToStringProb3.java","lastModified":1686480025645},{"path":"\/java8\/src\/com\/streams","parentWorkspace":"D:\/java_Vtalent\/spring","name":"StreamsMapExp.java","lastModified":1692264760671,"locationURI":"file:\/D:\/java_Vtalent\/spring\/java8\/src\/com\/streams\/StreamsMapExp.java"},{"path":"\/secondSpring\/src\/main\/java\/com\/springXml","parentWorkspace":"D:\/java_Vtalent\/spring","name":"Driver.java","lastModified":1693327006277,"locationURI":"file:\/D:\/java_Vtalent\/spring\/secondSpring\/src\/main\/java\/com\/springXml\/Driver.java"},{"path":"\/Java8PPT\/src\/com\/localtimeanddate","parentWorkspace":"D:\/java_Vtalent\/spring","name":"DateTimeZone.java","lastModified":1693923092102,"locationURI":"file:\/D:\/java_Vtalent\/spring\/Java8PPT\/src\/com\/localtimeanddate\/DateTimeZone.java"},{"path":"\/encode11\/src\/main\/java\/com\/encode","parentWorkspace":"D:\/java_Vtalent\/spring","name":"Encoder.java","lastModified":1694487585884,"locationURI":"file:\/D:\/java_Vtalent\/spring\/encode11\/src\/main\/java\/com\/encode\/Encoder.java"},{"path":"\/java8\/src\/com\/streams","parentWorkspace":"D:\/java_Vtalent\/spring","name":"MapExample1.java","lastModified":1692281013838,"locationURI":"file:\/D:\/java_Vtalent\/spring\/java8\/src\/com\/streams\/MapExample1.java"},{"path":"\/com.classAssignments\/src\/com\/stringsPractice","parentWorkspace":"D:\/java_Vtalent\/spring","name":"StringPalindromeInJavaProblem10.java","lastModified":1690257735006},{"path":"\/com.classAssignments\/src\/com\/multiThreadImplemetnsRunnable","parentWorkspace":"D:\/java_Vtalent\/spring","name":"BankApplicationTest.java","lastModified":1689687271869,"locationURI":"file:\/D:\/java_Vtalent\/spring\/com.classAssignments\/src\/com\/multiThreadImplemetnsRunnable\/BankApplicationTest.java"},{"path":"\/com.classAssignments\/src\/com\/exceptionsHandling","parentWorkspace":"D:\/java_Vtalent\/spring","name":"MyException.java","lastModified":1689051371499,"locationURI":"file:\/D:\/java_Vtalent\/spring\/com.classAssignments\/src\/com\/exceptionsHandling\/MyException.java"},{"path":"\/secondSpring","parentWorkspace":"D:\/java_Vtalent\/spring","name":"pom.xml","lastModified":1693273934454,"locationURI":"file:\/D:\/java_Vtalent\/spring\/secondSpring\/pom.xml"},{"path":"\/java8\/src\/com\/streams","parentWorkspace":"D:\/java_Vtalent\/spring","name":"GivenListOfIntegersFindAllNumbersStartingWith1.java","lastModified":1692276431162,"locationURI":"file:\/D:\/java_Vtalent\/spring\/java8\/src\/com\/streams\/GivenListOfIntegersFindAllNumbersStartingWith1.java"},{"path":"\/com.classAssignments\/src\/com\/stringsAssignments","parentWorkspace":"D:\/java_Vtalent\/spring","name":"JavaProgramMoveAllUppercaseCharactersToEndPage2_5.java","lastModified":1686316329549},{"path":"\/sample\/src\/main\/java","parentWorkspace":"D:\/java_Vtalent\/spring","name":"Encoder.java","lastModified":1694456228883,"locationURI":"file:\/D:\/java_Vtalent\/spring\/sample\/src\/main\/java\/Encoder.java"},{"path":"\/Java8PPT\/src\/com\/lambdaexpression","parentWorkspace":"D:\/java_Vtalent\/spring","name":"Example2.java","lastModified":1694279996349,"locationURI":"file:\/D:\/java_Vtalent\/spring\/Java8PPT\/src\/com\/lambdaexpression\/Example2.java"},{"path":"\/collections\/src\/com\/linkedlist","parentWorkspace":"D:\/java_Vtalent\/spring","name":"LinkedListmethods.java","lastModified":1691827124908,"locationURI":"file:\/D:\/java_Vtalent\/spring\/collections\/src\/com\/linkedlist\/LinkedListmethods.java"},{"path":"\/secondSpring\/src\/main\/java\/com\/mavenexample\/secondSpring","parentWorkspace":"D:\/java_Vtalent\/spring","name":"Car.java","lastModified":1693295316631,"locationURI":"file:\/D:\/java_Vtalent\/spring\/secondSpring\/src\/main\/java\/com\/mavenexample\/secondSpring\/Car.java"},{"path":"\/com.classAssignments\/src\/com\/stringsPractice","parentWorkspace":"D:\/java_Vtalent\/spring","name":"JavaForEachCharacterInStringProblem5.java","lastModified":1686050776767},{"path":"\/com.classAssignments\/src\/com\/multiThreadingExtendningThreadClass","parentWorkspace":"D:\/java_Vtalent\/spring","name":"Find_Even_Odd_Number.java","lastModified":1688968044032,"locationURI":"file:\/D:\/java_Vtalent\/spring\/com.classAssignments\/src\/com\/multiThreadingExtendningThreadClass\/Find_Even_Odd_Number.java"},{"path":"\/com.classAssignments\/src\/com\/classAssignments8And9And10","parentWorkspace":"D:\/java_Vtalent\/spring","name":"equalsOnStringAndStringBufferObjectsInJava8_5.java","lastModified":1686498992239},{"path":"\/collections","parentWorkspace":"D:\/java_Vtalent\/spring","name":"db.properties","lastModified":1692184082927,"locationURI":"file:\/D:\/java_Vtalent\/spring\/collections\/db.properties"},{"path":"\/com.classAssignments\/src\/com\/reviseStrings","parentWorkspace":"D:\/java_Vtalent\/spring","name":"PanagramString.java","lastModified":1686729372436,"locationURI":"file:\/D:\/java_Vtalent\/spring\/com.classAssignments\/src\/com\/reviseStrings\/PanagramString.java"},{"path":"\/java8\/src\/com\/collectorsStream","parentWorkspace":"D:\/java_Vtalent\/spring","name":"GroupingAndCountWordsByLength.java","lastModified":1692443121585,"locationURI":"file:\/D:\/java_Vtalent\/spring\/java8\/src\/com\/collectorsStream\/GroupingAndCountWordsByLength.java"},{"path":"\/trai1\/src\/trai1","parentWorkspace":"D:\/java_Vtalent\/spring","name":"FindNameInString.java","lastModified":1693832475041,"locationURI":"file:\/D:\/java_Vtalent\/spring\/trai1\/src\/trai1\/FindNameInString.java"},{"path":"\/trai1\/src\/general_practice","parentWorkspace":"D:\/java_Vtalent\/spring","name":"dispayDigitsOfNumber.java","lastModified":1684576429076},{"path":"\/com.classAssignments\/src\/com\/stringsAssignments","parentWorkspace":"D:\/java_Vtalent\/spring","name":"JavaProgramToPrintAllUniqueWordsOfStringPage2_1.java","lastModified":1686488087174},{"path":"\/FileHandling\/src\/com\/filehandling","parentWorkspace":"D:\/java_Vtalent\/spring","name":"MergerTwoFiles.java","lastModified":1690361308709,"locationURI":"file:\/D:\/java_Vtalent\/spring\/FileHandling\/src\/com\/filehandling\/MergerTwoFiles.java"},{"path":"\/com.classAssignments\/src\/com\/generics","parentWorkspace":"D:\/java_Vtalent\/spring","name":"GeneticsClass.java","lastModified":1691641825415,"locationURI":"file:\/D:\/java_Vtalent\/spring\/com.classAssignments\/src\/com\/generics\/GeneticsClass.java"},{"path":"\/Java8PPT\/src\/com\/java8\/collectionsenhancements","parentWorkspace":"D:\/java_Vtalent\/spring","name":"CollectionEnhancement_removeIf.java","lastModified":1694339899152,"locationURI":"file:\/D:\/java_Vtalent\/spring\/Java8PPT\/src\/com\/java8\/collectionsenhancements\/CollectionEnhancement_removeIf.java"},{"path":"\/com.classAssignments\/src\/com\/stringsPractice","parentWorkspace":"D:\/java_Vtalent\/spring","name":"HowToReverseStringJavaProblem9.java","lastModified":1686295687422},{"path":"\/com.classAssignments\/src\/com\/arrraysPractice","parentWorkspace":"D:\/java_Vtalent\/spring","name":"MinLengthOfWordAndIndexArrays.java","lastModified":1690474359809,"locationURI":"file:\/D:\/java_Vtalent\/spring\/com.classAssignments\/src\/com\/arrraysPractice\/MinLengthOfWordAndIndexArrays.java"},{"path":"\/com.classAssignments\/src\/com\/exceptionsHandling","parentWorkspace":"D:\/java_Vtalent\/spring","name":"InvlaidAgeExcpetion.java","lastModified":1688919671573,"locationURI":"file:\/D:\/java_Vtalent\/spring\/com.classAssignments\/src\/com\/exceptionsHandling\/InvlaidAgeExcpetion.java"},{"path":"\/com.classAssignments\/src\/com\/classAssignmentsPage6And7","parentWorkspace":"D:\/java_Vtalent\/spring","name":"GenerateRandomStringOfGivenSize4.java","lastModified":1686484524588},{"path":"\/com.classAssignments\/src\/com\/stringsAssignments","parentWorkspace":"D:\/java_Vtalent\/spring","name":"JavaProgramToIllustrateStringInterpolation.java","lastModified":1686297279052},{"path":"\/trai1\/src","parentWorkspace":"D:\/java_Vtalent\/spring","name":"MyDemo.java","lastModified":1691638140736,"locationURI":"file:\/D:\/java_Vtalent\/spring\/trai1\/src\/MyDemo.java"},{"path":"\/SpringbootFirst\/src\/main\/java\/com\/examplespringboot","parentWorkspace":"D:\/java_Vtalent\/spring","name":"CacheManager.java","lastModified":1694484642655,"locationURI":"file:\/D:\/java_Vtalent\/spring\/SpringbootFirst\/src\/main\/java\/com\/examplespringboot\/CacheManager.java"},{"path":"\/collections\/src\/com\/collectionInterface","parentWorkspace":"D:\/java_Vtalent\/spring","name":"ComparatorExp.java","lastModified":1692204806543,"locationURI":"file:\/D:\/java_Vtalent\/spring\/collections\/src\/com\/collectionInterface\/ComparatorExp.java"},{"path":"\/java8\/src\/com\/collectorsStream","parentWorkspace":"D:\/java_Vtalent\/spring","name":"CollectorsExamples.java","lastModified":1692429906841,"locationURI":"file:\/D:\/java_Vtalent\/spring\/java8\/src\/com\/collectorsStream\/CollectorsExamples.java"},{"path":"\/springFramework\/src\/com\/strategyDesignPattren","parentWorkspace":"D:\/java_Vtalent\/spring","name":"CreditCard.java","lastModified":1692689801190,"locationURI":"file:\/D:\/java_Vtalent\/spring\/springFramework\/src\/com\/strategyDesignPattren\/CreditCard.java"},{"path":"\/Java8PPT\/src\/com\/localtimeanddate","parentWorkspace":"D:\/java_Vtalent\/spring","name":"LocalDateExample.java","lastModified":1693911765670,"locationURI":"file:\/D:\/java_Vtalent\/spring\/Java8PPT\/src\/com\/localtimeanddate\/LocalDateExample.java"},{"path":"\/java8\/src\/com\/streams","parentWorkspace":"D:\/java_Vtalent\/spring","name":"StreamMapExamples.java","lastModified":1692282847158,"locationURI":"file:\/D:\/java_Vtalent\/spring\/java8\/src\/com\/streams\/StreamMapExamples.java"},{"path":"\/com.classAssignments\/src\/com\/methodsOnStrings","parentWorkspace":"D:\/java_Vtalent\/spring","name":"SwapFirstAndLastCharacterOfStringPage4_6.java","lastModified":1687138296025,"locationURI":"file:\/D:\/java_Vtalent\/spring\/com.classAssignments\/src\/com\/methodsOnStrings\/SwapFirstAndLastCharacterOfStringPage4_6.java"},{"path":"\/com.classAssignments\/src\/com\/stringsPractice","parentWorkspace":"D:\/java_Vtalent\/spring","name":"FindSumOfDigitsInStringProblem6.java","lastModified":1686230561513},{"path":"\/FileHandling\/src\/com\/filehandling","parentWorkspace":"D:\/java_Vtalent\/spring","name":"SameName.java","lastModified":1690361308709,"locationURI":"file:\/D:\/java_Vtalent\/spring\/FileHandling\/src\/com\/filehandling\/SameName.java"},{"path":"\/com.classAssignments\/src\/com\/generics","parentWorkspace":"D:\/java_Vtalent\/spring","name":"GenericBound1.java","lastModified":1691689429830,"locationURI":"file:\/D:\/java_Vtalent\/spring\/com.classAssignments\/src\/com\/generics\/GenericBound1.java"},{"path":"\/com.classAssignments\/src\/com\/arrraysPractice","parentWorkspace":"D:\/java_Vtalent\/spring","name":"SecondLargestNumberProblm14.java","lastModified":1685852925109},{"path":"\/trai1\/src","parentWorkspace":"D:\/java_Vtalent\/spring","name":"Employee.java","lastModified":1691291362546,"locationURI":"file:\/D:\/java_Vtalent\/spring\/trai1\/src\/Employee.java"},{"path":"\/springFramework\/src\/com\/strategyDesignPattren","parentWorkspace":"D:\/java_Vtalent\/spring","name":"BillCollector.java","lastModified":1692690617499,"locationURI":"file:\/D:\/java_Vtalent\/spring\/springFramework\/src\/com\/strategyDesignPattren\/BillCollector.java"},{"path":"\/com.classAssignments\/src\/com\/exceptionsHandling","parentWorkspace":"D:\/java_Vtalent\/spring","name":"ExceptionExp5.java","lastModified":1688748003099,"locationURI":"file:\/D:\/java_Vtalent\/spring\/com.classAssignments\/src\/com\/exceptionsHandling\/ExceptionExp5.java"},{"path":"\/Java8PPT\/src\/com\/defaultMethods","parentWorkspace":"D:\/java_Vtalent\/spring","name":"Idea.java","lastModified":1693187636571,"locationURI":"file:\/D:\/java_Vtalent\/spring\/Java8PPT\/src\/com\/defaultMethods\/Idea.java"},{"path":"\/com.classAssignments\/src\/com\/methodsOnStrings","parentWorkspace":"D:\/java_Vtalent\/spring","name":"Person.java","lastModified":1686985062440,"locationURI":"file:\/D:\/java_Vtalent\/spring\/com.classAssignments\/src\/com\/methodsOnStrings\/Person.java"},{"path":"\/Java8PPT\/src\/com\/functionalinterface","parentWorkspace":"D:\/java_Vtalent\/spring","name":"ConsumerExp1.java","lastModified":1694341315417,"locationURI":"file:\/D:\/java_Vtalent\/spring\/Java8PPT\/src\/com\/functionalinterface\/ConsumerExp1.java"},{"path":"\/Java8PPT\/src\/com\/streams","parentWorkspace":"D:\/java_Vtalent\/spring","name":"ForEachVsForEachOrdered.java","lastModified":1694054190095,"locationURI":"file:\/D:\/java_Vtalent\/spring\/Java8PPT\/src\/com\/streams\/ForEachVsForEachOrdered.java"},{"path":"\/com.classAssignments\/src\/com\/multiThreadImplemetnsRunnable","parentWorkspace":"D:\/java_Vtalent\/spring","name":"MyRunnable.java","lastModified":1689085648273,"locationURI":"file:\/D:\/java_Vtalent\/spring\/com.classAssignments\/src\/com\/multiThreadImplemetnsRunnable\/MyRunnable.java"},{"path":"\/java8\/src\/com\/collectorsStream","parentWorkspace":"D:\/java_Vtalent\/spring","name":"CalculatingAverageStudentGrade.java","lastModified":1692440597150,"locationURI":"file:\/D:\/java_Vtalent\/spring\/java8\/src\/com\/collectorsStream\/CalculatingAverageStudentGrade.java"},{"path":"\/springFramework\/src\/com\/strategyDesignPattren","parentWorkspace":"D:\/java_Vtalent\/spring","name":"Payment.java","lastModified":1692689801205,"locationURI":"file:\/D:\/java_Vtalent\/spring\/springFramework\/src\/com\/strategyDesignPattren\/Payment.java"},{"path":"\/com.classAssignments\/src\/com\/inheritance","parentWorkspace":"D:\/java_Vtalent\/spring","name":"Teacher.java","lastModified":1688125398549,"locationURI":"file:\/D:\/java_Vtalent\/spring\/com.classAssignments\/src\/com\/inheritance\/Teacher.java"},{"path":"\/com.classAssignments\/src\/com\/generics","parentWorkspace":"D:\/java_Vtalent\/spring","name":"GenericBound.java","lastModified":1691641993901,"locationURI":"file:\/D:\/java_Vtalent\/spring\/com.classAssignments\/src\/com\/generics\/GenericBound.java"},{"path":"\/encode11","parentWorkspace":"D:\/java_Vtalent\/spring","name":"pom.xml","lastModified":1694456192660,"locationURI":"file:\/D:\/java_Vtalent\/spring\/encode11\/pom.xml"},{"path":"\/com.classAssignments\/src\/com\/methodsOnStrings","parentWorkspace":"D:\/java_Vtalent\/spring","name":"Bb.java","lastModified":1687266868331,"locationURI":"file:\/D:\/java_Vtalent\/spring\/com.classAssignments\/src\/com\/methodsOnStrings\/Bb.java"},{"path":"\/com.classAssignments\/src\/com\/stringsAssignments","parentWorkspace":"D:\/java_Vtalent\/spring","name":"SwapFirstAndLastCharacterOfStringPage4_6.java","lastModified":1687138296016},{"path":"\/FileHandling\/src\/com\/filehandling","parentWorkspace":"D:\/java_Vtalent\/spring","name":"FileStatus.java","lastModified":1690390363208,"locationURI":"file:\/D:\/java_Vtalent\/spring\/FileHandling\/src\/com\/filehandling\/FileStatus.java"},{"path":"\/com.classAssignments\/src\/com\/collections","parentWorkspace":"D:\/java_Vtalent\/spring","name":"SynMap.java","lastModified":1691638139223,"locationURI":"file:\/D:\/java_Vtalent\/spring\/com.classAssignments\/src\/com\/collections\/SynMap.java"},{"path":"\/com.classAssignments\/src\/com\/stringsAssignments","parentWorkspace":"D:\/java_Vtalent\/spring","name":"JavaProgramToConvertStringToStringArray.java","lastModified":1686297691075},{"path":"\/collections\/src\/com\/collectionInterface","parentWorkspace":"D:\/java_Vtalent\/spring","name":"CollectionsMethods.java","lastModified":1691638137687,"locationURI":"file:\/D:\/java_Vtalent\/spring\/collections\/src\/com\/collectionInterface\/CollectionsMethods.java"},{"path":"\/Java8PPT\/src\/com\/java8\/collectionsenhancements","parentWorkspace":"D:\/java_Vtalent\/spring","name":"CollectionEnhancement_ForEach2.java","lastModified":1693501665019,"locationURI":"file:\/D:\/java_Vtalent\/spring\/Java8PPT\/src\/com\/java8\/collectionsenhancements\/CollectionEnhancement_ForEach2.java"},{"path":"\/com.classAssignments\/src\/com\/exceptionsHandling","parentWorkspace":"D:\/java_Vtalent\/spring","name":"VoteEligiblityException.java","lastModified":1689126120180,"locationURI":"file:\/D:\/java_Vtalent\/spring\/com.classAssignments\/src\/com\/exceptionsHandling\/VoteEligiblityException.java"},{"path":"\/com.classAssignments\/src\/com\/serialization","parentWorkspace":"D:\/java_Vtalent\/spring","name":"Person.java","lastModified":1690385875816,"locationURI":"file:\/D:\/java_Vtalent\/spring\/com.classAssignments\/src\/com\/serialization\/Person.java"},{"path":"\/DateAndTime\/src\/com\/datedemo","parentWorkspace":"D:\/java_Vtalent\/spring","name":"TimeZoneDemo.java","lastModified":1693116684334,"locationURI":"file:\/D:\/java_Vtalent\/spring\/DateAndTime\/src\/com\/datedemo\/TimeZoneDemo.java"},{"path":"\/com.classAssignments\/src\/com\/arrraysPractice","parentWorkspace":"D:\/java_Vtalent\/spring","name":"CopyOfArrayProblem9.java","lastModified":1690472463246,"locationURI":"file:\/D:\/java_Vtalent\/spring\/com.classAssignments\/src\/com\/arrraysPractice\/CopyOfArrayProblem9.java"},{"path":"\/DateAndTime\/src\/com\/datedemo","parentWorkspace":"D:\/java_Vtalent\/spring","name":"LocalDateTimeJava8.java","lastModified":1693018508834,"locationURI":"file:\/D:\/java_Vtalent\/spring\/DateAndTime\/src\/com\/datedemo\/LocalDateTimeJava8.java"},{"path":"\/com.classAssignments\/src\/com\/classAssignmentsPage6And7","parentWorkspace":"D:\/java_Vtalent\/spring","name":"RemoveExtraDelimiterFromString.java","lastModified":1686910335935},{"path":"\/springFramework\/src\/com\/strategyDesignPattren","parentWorkspace":"D:\/java_Vtalent\/spring","name":"Test.java","lastModified":1692849217677,"locationURI":"file:\/D:\/java_Vtalent\/spring\/springFramework\/src\/com\/strategyDesignPattren\/Test.java"},{"path":"\/userReg","parentWorkspace":"D:\/java_Vtalent\/spring","name":"pom.xml","lastModified":1694456584314,"locationURI":"file:\/D:\/java_Vtalent\/spring\/userReg\/pom.xml"},{"path":"\/java8\/src\/com\/functionalinterface","parentWorkspace":"D:\/java_Vtalent\/spring","name":"AnonymousClass.java","lastModified":1693327132517,"locationURI":"file:\/D:\/java_Vtalent\/spring\/java8\/src\/com\/functionalinterface\/AnonymousClass.java"},{"path":"\/com.classAssignments\/src","parentWorkspace":"D:\/java_Vtalent\/spring","name":"Test.java","lastModified":1687846781950,"locationURI":"file:\/D:\/java_Vtalent\/spring\/com.classAssignments\/src\/Test.java"},{"path":"\/userReg\/src\/main\/java\/userReg","parentWorkspace":"D:\/java_Vtalent\/spring","name":"Registration.java","lastModified":1694456878865,"locationURI":"file:\/D:\/java_Vtalent\/spring\/userReg\/src\/main\/java\/userReg\/Registration.java"},{"path":"\/com.classAssignments\/src\/com\/arrraysPractice","parentWorkspace":"D:\/java_Vtalent\/spring","name":"DifferentWaysToPrintArrayProblem4.java","lastModified":1689126066386,"locationURI":"file:\/D:\/java_Vtalent\/spring\/com.classAssignments\/src\/com\/arrraysPractice\/DifferentWaysToPrintArrayProblem4.java"},{"path":"\/com.classAssignments\/src\/com\/exceptionsHandling","parentWorkspace":"D:\/java_Vtalent\/spring","name":"SubClass.java","lastModified":1688747763199,"locationURI":"file:\/D:\/java_Vtalent\/spring\/com.classAssignments\/src\/com\/exceptionsHandling\/SubClass.java"},{"path":"\/com.classAssignments\/src\/com\/methodsOnStrings","parentWorkspace":"D:\/java_Vtalent\/spring","name":"practice1Method.java","lastModified":1687187682549,"locationURI":"file:\/D:\/java_Vtalent\/spring\/com.classAssignments\/src\/com\/methodsOnStrings\/practice1Method.java"},{"path":"\/com.classAssignments\/src\/com\/stringsAssignments","parentWorkspace":"D:\/java_Vtalent\/spring","name":"SwapCornerWordsAndReverseMiddleCharactersOfStringPage2_3.java","lastModified":1687138176183},{"path":"\/com.classAssignments\/src\/com\/stringsAssignments","parentWorkspace":"D:\/java_Vtalent\/spring","name":"RemoveFirstAndLastCharacterOfStringPage4_7.java","lastModified":1686474752101},{"path":"\/com.classAssignments\/src\/com\/stringsAssignments","parentWorkspace":"D:\/java_Vtalent\/spring","name":"CountNumberOfVowelsPage2_10.java","lastModified":1686317239525},{"path":"\/com.classAssignments\/src\/com\/methodsOnStrings","parentWorkspace":"D:\/java_Vtalent\/spring","name":"JavaProgramToPrintAllUniqueWordsOfStringPage2_1.java","lastModified":1687136124182,"locationURI":"file:\/D:\/java_Vtalent\/spring\/com.classAssignments\/src\/com\/methodsOnStrings\/JavaProgramToPrintAllUniqueWordsOfStringPage2_1.java"},{"path":"\/collections\/src\/com\/collectionInterface","parentWorkspace":"D:\/java_Vtalent\/spring","name":"ArrayListMethods.java","lastModified":1691914955503,"locationURI":"file:\/D:\/java_Vtalent\/spring\/collections\/src\/com\/collectionInterface\/ArrayListMethods.java"},{"path":"\/Java8PPT\/src\/com\/lambdaexpression","parentWorkspace":"D:\/java_Vtalent\/spring","name":"Example1.java","lastModified":1694278126209,"locationURI":"file:\/D:\/java_Vtalent\/spring\/Java8PPT\/src\/com\/lambdaexpression\/Example1.java"},{"path":"\/com.classAssignments\/src\/com\/methodsOnStrings","parentWorkspace":"D:\/java_Vtalent\/spring","name":"CountNumberOfVowelsPage2_10.java","lastModified":1687134252960,"locationURI":"file:\/D:\/java_Vtalent\/spring\/com.classAssignments\/src\/com\/methodsOnStrings\/CountNumberOfVowelsPage2_10.java"},{"path":"\/DateAndTime\/src\/com\/datedemo","parentWorkspace":"D:\/java_Vtalent\/spring","name":"DateDemoJava8.java","lastModified":1693017371147,"locationURI":"file:\/D:\/java_Vtalent\/spring\/DateAndTime\/src\/com\/datedemo\/DateDemoJava8.java"},{"path":"\/java8\/src\/com\/functionalinterface","parentWorkspace":"D:\/java_Vtalent\/spring","name":"ComparableLambdaExample.java","lastModified":1691939651598,"locationURI":"file:\/D:\/java_Vtalent\/spring\/java8\/src\/com\/functionalinterface\/ComparableLambdaExample.java"},{"path":"\/java8\/src\/com\/streams","parentWorkspace":"D:\/java_Vtalent\/spring","name":"FilterDemo3.java","lastModified":1692183571879,"locationURI":"file:\/D:\/java_Vtalent\/spring\/java8\/src\/com\/streams\/FilterDemo3.java"},{"path":"\/com.classAssignments\/src\/com\/constructors","parentWorkspace":"D:\/java_Vtalent\/spring","name":"Demo.java","lastModified":1689523746087,"locationURI":"file:\/D:\/java_Vtalent\/spring\/com.classAssignments\/src\/com\/constructors\/Demo.java"},{"path":"\/java8\/src\/com\/streams","parentWorkspace":"D:\/java_Vtalent\/spring","name":"MainClassForStudentsMapVsFlatMap.java","lastModified":1692330523863,"locationURI":"file:\/D:\/java_Vtalent\/spring\/java8\/src\/com\/streams\/MainClassForStudentsMapVsFlatMap.java"},{"path":"\/trai1\/src\/com\/tata","parentWorkspace":"D:\/java_Vtalent\/spring","name":"Engine.java","lastModified":1688577090060,"locationURI":"file:\/D:\/java_Vtalent\/spring\/trai1\/src\/com\/tata\/Engine.java"},{"path":"\/Java8PPT\/src\/com\/localtimeanddate","parentWorkspace":"D:\/java_Vtalent\/spring","name":"ClassB.java","lastModified":1693625658442,"locationURI":"file:\/D:\/java_Vtalent\/spring\/Java8PPT\/src\/com\/localtimeanddate\/ClassB.java"},{"path":"\/com.classAssignments\/src\/com\/methodsOnStrings","parentWorkspace":"D:\/java_Vtalent\/spring","name":"SwapCornerWordsAndReverseMiddleCharactersOfStringPage2_3.java","lastModified":1689126120180,"locationURI":"file:\/D:\/java_Vtalent\/spring\/com.classAssignments\/src\/com\/methodsOnStrings\/SwapCornerWordsAndReverseMiddleCharactersOfStringPage2_3.java"},{"path":"\/com.classAssignments\/src\/com\/multiThreadingExtendningThreadClass","parentWorkspace":"D:\/java_Vtalent\/spring","name":"MultiThreadExp1.java","lastModified":1688960816881,"locationURI":"file:\/D:\/java_Vtalent\/spring\/com.classAssignments\/src\/com\/multiThreadingExtendningThreadClass\/MultiThreadExp1.java"},{"path":"\/Java8PPT\/src\/com\/java8\/collectionsenhancements","parentWorkspace":"D:\/java_Vtalent\/spring","name":"CollectionEnhancement_ForEach.java","lastModified":1693501665042,"locationURI":"file:\/D:\/java_Vtalent\/spring\/Java8PPT\/src\/com\/java8\/collectionsenhancements\/CollectionEnhancement_ForEach.java"},{"path":"\/com.classAssignments\/src\/com\/stringsAssignments","parentWorkspace":"D:\/java_Vtalent\/spring","name":"RemoveGivenWordFromStringPage2_4.java","lastModified":1686315649698},{"path":"\/com.classAssignments\/src\/com\/multiThreadImplemetnsRunnable","parentWorkspace":"D:\/java_Vtalent\/spring","name":"Demo.java","lastModified":1689128990960,"locationURI":"file:\/D:\/java_Vtalent\/spring\/com.classAssignments\/src\/com\/multiThreadImplemetnsRunnable\/Demo.java"},{"path":"\/java8\/src\/com\/streams","parentWorkspace":"D:\/java_Vtalent\/spring","name":"MapExp3NumberSquareAvg.java","lastModified":1692286896841,"locationURI":"file:\/D:\/java_Vtalent\/spring\/java8\/src\/com\/streams\/MapExp3NumberSquareAvg.java"},{"path":"\/java8\/src\/com\/streams","parentWorkspace":"D:\/java_Vtalent\/spring","name":"StramLimitDistinctSkipDemo.java","lastModified":1692271059964,"locationURI":"file:\/D:\/java_Vtalent\/spring\/java8\/src\/com\/streams\/StramLimitDistinctSkipDemo.java"},{"path":"\/Java8PPT\/src\/com\/methodrefernace","parentWorkspace":"D:\/java_Vtalent\/spring","name":"Test.java","lastModified":1693936719386,"locationURI":"file:\/D:\/java_Vtalent\/spring\/Java8PPT\/src\/com\/methodrefernace\/Test.java"},{"path":"\/Java8PPT\/src\/com\/defaultMethods","parentWorkspace":"D:\/java_Vtalent\/spring","name":"Test1.java","lastModified":1693204554717,"locationURI":"file:\/D:\/java_Vtalent\/spring\/Java8PPT\/src\/com\/defaultMethods\/Test1.java"},{"path":"\/FileHandling\/src\/com\/filehandling","parentWorkspace":"D:\/java_Vtalent\/spring","name":"ExternExample.java","lastModified":1690392223680,"locationURI":"file:\/D:\/java_Vtalent\/spring\/FileHandling\/src\/com\/filehandling\/ExternExample.java"},{"path":"\/collections\/src\/com\/collectionInterface","parentWorkspace":"D:\/java_Vtalent\/spring","name":"FindDuplicatesNumbers.java","lastModified":1691858932785,"locationURI":"file:\/D:\/java_Vtalent\/spring\/collections\/src\/com\/collectionInterface\/FindDuplicatesNumbers.java"}]}